{".class": "MypyFile", "_fullname": "django.db.models.fields.files", "is_partial_stub_package": false, "is_stub": false, "names": {".class": "SymbolTable", "DeferredAttribute": {".class": "SymbolTableNode", "cross_ref": "django.db.models.query_utils.DeferredAttribute", "kind": "Gdef"}, "Field": {".class": "SymbolTableNode", "cross_ref": "django.db.models.fields.Field", "kind": "Gdef"}, "FieldFile": {".class": "SymbolTableNode", "kind": "Gdef", "node": {".class": "TypeInfo", "_promote": null, "abstract_attributes": [], "bases": ["django.core.files.base.File"], "declared_metaclass": null, "defn": {".class": "ClassDef", "fullname": "django.db.models.fields.files.FieldFile", "name": "FieldFile", "type_vars": []}, "flags": [], "fullname": "django.db.models.fields.files.FieldFile", "metaclass_type": null, "metadata": {}, "module_name": "django.db.models.fields.files", "mro": ["django.db.models.fields.files.FieldFile", "django.core.files.base.File", "django.core.files.utils.FileProxyMixin", "builtins.object"], "names": {".class": "SymbolTable", "__eq__": {".class": "SymbolTableNode", "kind": "Mdef", "node": {".class": "FuncDef", "arg_kinds": [0, 0], "arg_names": ["self", "other"], "flags": [], "fullname": "django.db.models.fields.files.FieldFile.__eq__", "name": "__eq__", "type": null}}, "__getstate__": {".class": "SymbolTableNode", "kind": "Mdef", "node": {".class": "FuncDef", "arg_kinds": [0], "arg_names": ["self"], "flags": [], "fullname": "django.db.models.fields.files.FieldFile.__getstate__", "name": "__getstate__", "type": null}}, "__hash__": {".class": "SymbolTableNode", "kind": "Mdef", "node": {".class": "FuncDef", "arg_kinds": [0], "arg_names": ["self"], "flags": [], "fullname": "django.db.models.fields.files.FieldFile.__hash__", "name": "__hash__", "type": null}}, "__init__": {".class": "SymbolTableNode", "kind": "Mdef", "node": {".class": "FuncDef", "arg_kinds": [0, 0, 0, 0], "arg_names": ["self", "instance", "field", "name"], "flags": [], "fullname": "django.db.models.fields.files.FieldFile.__init__", "name": "__init__", "type": null}}, "__setstate__": {".class": "SymbolTableNode", "kind": "Mdef", "node": {".class": "FuncDef", "arg_kinds": [0, 0], "arg_names": ["self", "state"], "flags": [], "fullname": "django.db.models.fields.files.FieldFile.__setstate__", "name": "__setstate__", "type": null}}, "_committed": {".class": "SymbolTableNode", "implicit": true, "kind": "Mdef", "node": {".class": "Var", "flags": [], "fullname": "django.db.models.fields.files.FieldFile._committed", "name": "_committed", "type": {".class": "AnyType", "missing_import_name": null, "source_any": null, "type_of_any": 1}}}, "_del_file": {".class": "SymbolTableNode", "kind": "Mdef", "node": {".class": "FuncDef", "arg_kinds": [0], "arg_names": ["self"], "flags": [], "fullname": "django.db.models.fields.files.FieldFile._del_file", "name": "_del_file", "type": null}}, "_file": {".class": "SymbolTableNode", "implicit": true, "kind": "Mdef", "node": {".class": "Var", "flags": [], "fullname": "django.db.models.fields.files.FieldFile._file", "name": "_file", "type": {".class": "AnyType", "missing_import_name": null, "source_any": null, "type_of_any": 1}}}, "_get_file": {".class": "SymbolTableNode", "kind": "Mdef", "node": {".class": "FuncDef", "arg_kinds": [0], "arg_names": ["self"], "flags": [], "fullname": "django.db.models.fields.files.FieldFile._get_file", "name": "_get_file", "type": null}}, "_require_file": {".class": "SymbolTableNode", "kind": "Mdef", "node": {".class": "FuncDef", "arg_kinds": [0], "arg_names": ["self"], "flags": [], "fullname": "django.db.models.fields.files.FieldFile._require_file", "name": "_require_file", "type": null}}, "_set_file": {".class": "SymbolTableNode", "kind": "Mdef", "node": {".class": "FuncDef", "arg_kinds": [0, 0], "arg_names": ["self", "file"], "flags": [], "fullname": "django.db.models.fields.files.FieldFile._set_file", "name": "_set_file", "type": null}}, "close": {".class": "SymbolTableNode", "kind": "Mdef", "node": {".class": "FuncDef", "arg_kinds": [0], "arg_names": ["self"], "flags": [], "fullname": "django.db.models.fields.files.FieldFile.close", "name": "close", "type": null}}, "closed": {".class": "SymbolTableNode", "kind": "Mdef", "node": {".class": "Decorator", "func": {".class": "FuncDef", "arg_kinds": [0], "arg_names": ["self"], "flags": ["is_property", "is_decorated"], "fullname": "django.db.models.fields.files.FieldFile.closed", "name": "closed", "type": null}, "is_overload": false, "var": {".class": "Var", "flags": ["is_initialized_in_class", "is_property", "is_ready"], "fullname": null, "name": "closed", "type": {".class": "CallableType", "arg_kinds": [0], "arg_names": ["self"], "arg_types": ["django.db.models.fields.files.FieldFile"], "bound_args": [], "def_extras": {}, "fallback": "builtins.function", "implicit": true, "is_ellipsis_args": false, "name": "closed of FieldFile", "ret_type": {".class": "AnyType", "missing_import_name": null, "source_any": null, "type_of_any": 1}, "variables": []}}}}, "delete": {".class": "SymbolTableNode", "kind": "Mdef", "node": {".class": "FuncDef", "arg_kinds": [0, 1], "arg_names": ["self", "save"], "flags": [], "fullname": "django.db.models.fields.files.FieldFile.delete", "name": "delete", "type": null}}, "field": {".class": "SymbolTableNode", "implicit": true, "kind": "Mdef", "node": {".class": "Var", "flags": [], "fullname": "django.db.models.fields.files.FieldFile.field", "name": "field", "type": {".class": "AnyType", "missing_import_name": null, "source_any": null, "type_of_any": 1}}}, "file": {".class": "SymbolTableNode", "kind": "Mdef", "node": {".class": "Var", "flags": ["is_initialized_in_class"], "fullname": "django.db.models.fields.files.FieldFile.file", "name": "file", "type": "builtins.property"}}, "instance": {".class": "SymbolTableNode", "implicit": true, "kind": "Mdef", "node": {".class": "Var", "flags": [], "fullname": "django.db.models.fields.files.FieldFile.instance", "name": "instance", "type": {".class": "AnyType", "missing_import_name": null, "source_any": null, "type_of_any": 1}}}, "open": {".class": "SymbolTableNode", "kind": "Mdef", "node": {".class": "FuncDef", "arg_kinds": [0, 1], "arg_names": ["self", "mode"], "flags": [], "fullname": "django.db.models.fields.files.FieldFile.open", "name": "open", "type": null}}, "path": {".class": "SymbolTableNode", "kind": "Mdef", "node": {".class": "Decorator", "func": {".class": "FuncDef", "arg_kinds": [0], "arg_names": ["self"], "flags": ["is_property", "is_decorated"], "fullname": "django.db.models.fields.files.FieldFile.path", "name": "path", "type": null}, "is_overload": false, "var": {".class": "Var", "flags": ["is_initialized_in_class", "is_property", "is_ready"], "fullname": null, "name": "path", "type": {".class": "CallableType", "arg_kinds": [0], "arg_names": ["self"], "arg_types": ["django.db.models.fields.files.FieldFile"], "bound_args": [], "def_extras": {}, "fallback": "builtins.function", "implicit": true, "is_ellipsis_args": false, "name": "path of FieldFile", "ret_type": {".class": "AnyType", "missing_import_name": null, "source_any": null, "type_of_any": 1}, "variables": []}}}}, "save": {".class": "SymbolTableNode", "kind": "Mdef", "node": {".class": "FuncDef", "arg_kinds": [0, 0, 0, 1], "arg_names": ["self", "name", "content", "save"], "flags": [], "fullname": "django.db.models.fields.files.FieldFile.save", "name": "save", "type": null}}, "size": {".class": "SymbolTableNode", "kind": "Mdef", "node": {".class": "Decorator", "func": {".class": "FuncDef", "arg_kinds": [0], "arg_names": ["self"], "flags": ["is_property", "is_decorated"], "fullname": "django.db.models.fields.files.FieldFile.size", "name": "size", "type": null}, "is_overload": false, "var": {".class": "Var", "flags": ["is_initialized_in_class", "is_property", "is_ready"], "fullname": null, "name": "size", "type": {".class": "CallableType", "arg_kinds": [0], "arg_names": ["self"], "arg_types": ["django.db.models.fields.files.FieldFile"], "bound_args": [], "def_extras": {}, "fallback": "builtins.function", "implicit": true, "is_ellipsis_args": false, "name": "size of FieldFile", "ret_type": {".class": "AnyType", "missing_import_name": null, "source_any": null, "type_of_any": 1}, "variables": []}}}}, "storage": {".class": "SymbolTableNode", "implicit": true, "kind": "Mdef", "node": {".class": "Var", "flags": [], "fullname": "django.db.models.fields.files.FieldFile.storage", "name": "storage", "type": {".class": "AnyType", "missing_import_name": null, "source_any": null, "type_of_any": 1}}}, "url": {".class": "SymbolTableNode", "kind": "Mdef", "node": {".class": "Decorator", "func": {".class": "FuncDef", "arg_kinds": [0], "arg_names": ["self"], "flags": ["is_property", "is_decorated"], "fullname": "django.db.models.fields.files.FieldFile.url", "name": "url", "type": null}, "is_overload": false, "var": {".class": "Var", "flags": ["is_initialized_in_class", "is_property", "is_ready"], "fullname": null, "name": "url", "type": {".class": "CallableType", "arg_kinds": [0], "arg_names": ["self"], "arg_types": ["django.db.models.fields.files.FieldFile"], "bound_args": [], "def_extras": {}, "fallback": "builtins.function", "implicit": true, "is_ellipsis_args": false, "name": "url of FieldFile", "ret_type": {".class": "AnyType", "missing_import_name": null, "source_any": null, "type_of_any": 1}, "variables": []}}}}}, "tuple_type": null, "type_vars": [], "typeddict_type": null}}, "File": {".class": "SymbolTableNode", "cross_ref": "django.core.files.base.File", "kind": "Gdef"}, "FileDescriptor": {".class": "SymbolTableNode", "kind": "Gdef", "node": {".class": "TypeInfo", "_promote": null, "abstract_attributes": [], "bases": ["django.db.models.query_utils.DeferredAttribute"], "declared_metaclass": null, "defn": {".class": "ClassDef", "fullname": "django.db.models.fields.files.FileDescriptor", "name": "FileDescriptor", "type_vars": []}, "flags": [], "fullname": "django.db.models.fields.files.FileDescriptor", "metaclass_type": null, "metadata": {}, "module_name": "django.db.models.fields.files", "mro": ["django.db.models.fields.files.FileDescriptor", "django.db.models.query_utils.DeferredAttribute", "builtins.object"], "names": {".class": "SymbolTable", "__get__": {".class": "SymbolTableNode", "kind": "Mdef", "node": {".class": "FuncDef", "arg_kinds": [0, 0, 1], "arg_names": ["self", "instance", "cls"], "flags": [], "fullname": "django.db.models.fields.files.FileDescriptor.__get__", "name": "__get__", "type": null}}, "__set__": {".class": "SymbolTableNode", "kind": "Mdef", "node": {".class": "FuncDef", "arg_kinds": [0, 0, 0], "arg_names": ["self", "instance", "value"], "flags": [], "fullname": "django.db.models.fields.files.FileDescriptor.__set__", "name": "__set__", "type": null}}}, "tuple_type": null, "type_vars": [], "typeddict_type": null}}, "FileField": {".class": "SymbolTableNode", "kind": "Gdef", "node": {".class": "TypeInfo", "_promote": null, "abstract_attributes": [], "bases": ["django.db.models.fields.Field"], "declared_metaclass": null, "defn": {".class": "ClassDef", "fullname": "django.db.models.fields.files.FileField", "name": "FileField", "type_vars": []}, "flags": [], "fullname": "django.db.models.fields.files.FileField", "metaclass_type": null, "metadata": {}, "module_name": "django.db.models.fields.files", "mro": ["django.db.models.fields.files.FileField", "django.db.models.fields.Field", "django.db.models.query_utils.RegisterLookupMixin", "builtins.object"], "names": {".class": "SymbolTable", "__init__": {".class": "SymbolTableNode", "kind": "Mdef", "node": {".class": "FuncDef", "arg_kinds": [0, 1, 1, 1, 1, 4], "arg_names": ["self", "verbose_name", "name", "upload_to", "storage", "kwargs"], "flags": [], "fullname": "django.db.models.fields.files.FileField.__init__", "name": "__init__", "type": null}}, "_check_primary_key": {".class": "SymbolTableNode", "kind": "Mdef", "node": {".class": "FuncDef", "arg_kinds": [0], "arg_names": ["self"], "flags": [], "fullname": "django.db.models.fields.files.FileField._check_primary_key", "name": "_check_primary_key", "type": null}}, "_check_upload_to": {".class": "SymbolTableNode", "kind": "Mdef", "node": {".class": "FuncDef", "arg_kinds": [0], "arg_names": ["self"], "flags": [], "fullname": "django.db.models.fields.files.FileField._check_upload_to", "name": "_check_upload_to", "type": null}}, "_primary_key_set_explicitly": {".class": "SymbolTableNode", "implicit": true, "kind": "Mdef", "node": {".class": "Var", "flags": [], "fullname": "django.db.models.fields.files.FileField._primary_key_set_explicitly", "name": "_primary_key_set_explicitly", "type": {".class": "AnyType", "missing_import_name": null, "source_any": null, "type_of_any": 1}}}, "attr_class": {".class": "SymbolTableNode", "kind": "Mdef", "node": {".class": "Var", "flags": ["is_initialized_in_class"], "fullname": "django.db.models.fields.files.FileField.attr_class", "name": "attr_class", "type": {".class": "CallableType", "arg_kinds": [0, 0, 0], "arg_names": ["instance", "field", "name"], "arg_types": [{".class": "AnyType", "missing_import_name": null, "source_any": null, "type_of_any": 1}, {".class": "AnyType", "missing_import_name": null, "source_any": null, "type_of_any": 1}, {".class": "AnyType", "missing_import_name": null, "source_any": null, "type_of_any": 1}], "bound_args": ["django.db.models.fields.files.FieldFile"], "def_extras": {}, "fallback": "builtins.type", "implicit": true, "is_ellipsis_args": false, "name": null, "ret_type": "django.db.models.fields.files.FieldFile", "variables": []}}}, "check": {".class": "SymbolTableNode", "kind": "Mdef", "node": {".class": "FuncDef", "arg_kinds": [0, 4], "arg_names": ["self", "kwargs"], "flags": [], "fullname": "django.db.models.fields.files.FileField.check", "name": "check", "type": null}}, "contribute_to_class": {".class": "SymbolTableNode", "kind": "Mdef", "node": {".class": "FuncDef", "arg_kinds": [0, 0, 0, 4], "arg_names": ["self", "cls", "name", "kwargs"], "flags": [], "fullname": "django.db.models.fields.files.FileField.contribute_to_class", "name": "contribute_to_class", "type": null}}, "deconstruct": {".class": "SymbolTableNode", "kind": "Mdef", "node": {".class": "FuncDef", "arg_kinds": [0], "arg_names": ["self"], "flags": [], "fullname": "django.db.models.fields.files.FileField.deconstruct", "name": "deconstruct", "type": null}}, "description": {".class": "SymbolTableNode", "kind": "Mdef", "node": {".class": "Var", "flags": ["is_initialized_in_class"], "fullname": "django.db.models.fields.files.FileField.description", "name": "description", "type": {".class": "AnyType", "missing_import_name": null, "source_any": {".class": "AnyType", "missing_import_name": null, "source_any": null, "type_of_any": 1}, "type_of_any": 7}}}, "descriptor_class": {".class": "SymbolTableNode", "kind": "Mdef", "node": {".class": "Var", "flags": ["is_initialized_in_class"], "fullname": "django.db.models.fields.files.FileField.descriptor_class", "name": "descriptor_class", "type": {".class": "CallableType", "arg_kinds": [0], "arg_names": ["field"], "arg_types": [{".class": "AnyType", "missing_import_name": null, "source_any": null, "type_of_any": 1}], "bound_args": ["django.db.models.fields.files.FileDescriptor"], "def_extras": {}, "fallback": "builtins.type", "implicit": true, "is_ellipsis_args": false, "name": null, "ret_type": "django.db.models.fields.files.FileDescriptor", "variables": []}}}, "formfield": {".class": "SymbolTableNode", "kind": "Mdef", "node": {".class": "FuncDef", "arg_kinds": [0, 4], "arg_names": ["self", "kwargs"], "flags": [], "fullname": "django.db.models.fields.files.FileField.formfield", "name": "formfield", "type": null}}, "generate_filename": {".class": "SymbolTableNode", "kind": "Mdef", "node": {".class": "FuncDef", "arg_kinds": [0, 0, 0], "arg_names": ["self", "instance", "filename"], "flags": [], "fullname": "django.db.models.fields.files.FileField.generate_filename", "name": "generate_filename", "type": null}}, "get_internal_type": {".class": "SymbolTableNode", "kind": "Mdef", "node": {".class": "FuncDef", "arg_kinds": [0], "arg_names": ["self"], "flags": [], "fullname": "django.db.models.fields.files.FileField.get_internal_type", "name": "get_internal_type", "type": null}}, "get_prep_value": {".class": "SymbolTableNode", "kind": "Mdef", "node": {".class": "FuncDef", "arg_kinds": [0, 0], "arg_names": ["self", "value"], "flags": [], "fullname": "django.db.models.fields.files.FileField.get_prep_value", "name": "get_prep_value", "type": null}}, "pre_save": {".class": "SymbolTableNode", "kind": "Mdef", "node": {".class": "FuncDef", "arg_kinds": [0, 0, 0], "arg_names": ["self", "model_instance", "add"], "flags": [], "fullname": "django.db.models.fields.files.FileField.pre_save", "name": "pre_save", "type": null}}, "save_form_data": {".class": "SymbolTableNode", "kind": "Mdef", "node": {".class": "FuncDef", "arg_kinds": [0, 0, 0], "arg_names": ["self", "instance", "data"], "flags": [], "fullname": "django.db.models.fields.files.FileField.save_form_data", "name": "save_form_data", "type": null}}, "storage": {".class": "SymbolTableNode", "implicit": true, "kind": "Mdef", "node": {".class": "Var", "flags": [], "fullname": "django.db.models.fields.files.FileField.storage", "name": "storage", "type": {".class": "AnyType", "missing_import_name": null, "source_any": null, "type_of_any": 1}}}, "upload_to": {".class": "SymbolTableNode", "implicit": true, "kind": "Mdef", "node": {".class": "Var", "flags": [], "fullname": "django.db.models.fields.files.FileField.upload_to", "name": "upload_to", "type": {".class": "AnyType", "missing_import_name": null, "source_any": null, "type_of_any": 1}}}}, "tuple_type": null, "type_vars": [], "typeddict_type": null}}, "ImageField": {".class": "SymbolTableNode", "kind": "Gdef", "node": {".class": "TypeInfo", "_promote": null, "abstract_attributes": [], "bases": ["django.db.models.fields.files.FileField"], "declared_metaclass": null, "defn": {".class": "ClassDef", "fullname": "django.db.models.fields.files.ImageField", "name": "ImageField", "type_vars": []}, "flags": [], "fullname": "django.db.models.fields.files.ImageField", "metaclass_type": null, "metadata": {}, "module_name": "django.db.models.fields.files", "mro": ["django.db.models.fields.files.ImageField", "django.db.models.fields.files.FileField", "django.db.models.fields.Field", "django.db.models.query_utils.RegisterLookupMixin", "builtins.object"], "names": {".class": "SymbolTable", "__init__": {".class": "SymbolTableNode", "kind": "Mdef", "node": {".class": "FuncDef", "arg_kinds": [0, 1, 1, 1, 1, 4], "arg_names": ["self", "verbose_name", "name", "width_field", "height_field", "kwargs"], "flags": [], "fullname": "django.db.models.fields.files.ImageField.__init__", "name": "__init__", "type": null}}, "_check_image_library_installed": {".class": "SymbolTableNode", "kind": "Mdef", "node": {".class": "FuncDef", "arg_kinds": [0], "arg_names": ["self"], "flags": [], "fullname": "django.db.models.fields.files.ImageField._check_image_library_installed", "name": "_check_image_library_installed", "type": null}}, "attr_class": {".class": "SymbolTableNode", "kind": "Mdef", "node": {".class": "Var", "flags": ["is_initialized_in_class"], "fullname": "django.db.models.fields.files.ImageField.attr_class", "name": "attr_class", "type": {".class": "CallableType", "arg_kinds": [0, 0, 0], "arg_names": ["instance", "field", "name"], "arg_types": [{".class": "AnyType", "missing_import_name": null, "source_any": null, "type_of_any": 1}, {".class": "AnyType", "missing_import_name": null, "source_any": null, "type_of_any": 1}, {".class": "AnyType", "missing_import_name": null, "source_any": null, "type_of_any": 1}], "bound_args": ["django.db.models.fields.files.ImageFieldFile"], "def_extras": {}, "fallback": "builtins.type", "implicit": true, "is_ellipsis_args": false, "name": null, "ret_type": "django.db.models.fields.files.ImageFieldFile", "variables": []}}}, "check": {".class": "SymbolTableNode", "kind": "Mdef", "node": {".class": "FuncDef", "arg_kinds": [0, 4], "arg_names": ["self", "kwargs"], "flags": [], "fullname": "django.db.models.fields.files.ImageField.check", "name": "check", "type": null}}, "contribute_to_class": {".class": "SymbolTableNode", "kind": "Mdef", "node": {".class": "FuncDef", "arg_kinds": [0, 0, 0, 4], "arg_names": ["self", "cls", "name", "kwargs"], "flags": [], "fullname": "django.db.models.fields.files.ImageField.contribute_to_class", "name": "contribute_to_class", "type": null}}, "deconstruct": {".class": "SymbolTableNode", "kind": "Mdef", "node": {".class": "FuncDef", "arg_kinds": [0], "arg_names": ["self"], "flags": [], "fullname": "django.db.models.fields.files.ImageField.deconstruct", "name": "deconstruct", "type": null}}, "description": {".class": "SymbolTableNode", "kind": "Mdef", "node": {".class": "Var", "flags": ["is_initialized_in_class"], "fullname": "django.db.models.fields.files.ImageField.description", "name": "description", "type": {".class": "AnyType", "missing_import_name": null, "source_any": {".class": "AnyType", "missing_import_name": null, "source_any": null, "type_of_any": 1}, "type_of_any": 7}}}, "descriptor_class": {".class": "SymbolTableNode", "kind": "Mdef", "node": {".class": "Var", "flags": ["is_initialized_in_class"], "fullname": "django.db.models.fields.files.ImageField.descriptor_class", "name": "descriptor_class", "type": {".class": "CallableType", "arg_kinds": [0], "arg_names": ["field"], "arg_types": [{".class": "AnyType", "missing_import_name": null, "source_any": null, "type_of_any": 1}], "bound_args": ["django.db.models.fields.files.ImageFileDescriptor"], "def_extras": {}, "fallback": "builtins.type", "implicit": true, "is_ellipsis_args": false, "name": null, "ret_type": "django.db.models.fields.files.ImageFileDescriptor", "variables": []}}}, "formfield": {".class": "SymbolTableNode", "kind": "Mdef", "node": {".class": "FuncDef", "arg_kinds": [0, 4], "arg_names": ["self", "kwargs"], "flags": [], "fullname": "django.db.models.fields.files.ImageField.formfield", "name": "formfield", "type": null}}, "height_field": {".class": "SymbolTableNode", "implicit": true, "kind": "Mdef", "node": {".class": "Var", "flags": [], "fullname": "django.db.models.fields.files.ImageField.height_field", "name": "height_field", "type": {".class": "AnyType", "missing_import_name": null, "source_any": null, "type_of_any": 1}}}, "update_dimension_fields": {".class": "SymbolTableNode", "kind": "Mdef", "node": {".class": "FuncDef", "arg_kinds": [0, 0, 1, 2, 4], "arg_names": ["self", "instance", "force", "args", "kwargs"], "flags": [], "fullname": "django.db.models.fields.files.ImageField.update_dimension_fields", "name": "update_dimension_fields", "type": null}}, "width_field": {".class": "SymbolTableNode", "implicit": true, "kind": "Mdef", "node": {".class": "Var", "flags": [], "fullname": "django.db.models.fields.files.ImageField.width_field", "name": "width_field", "type": {".class": "AnyType", "missing_import_name": null, "source_any": null, "type_of_any": 1}}}}, "tuple_type": null, "type_vars": [], "typeddict_type": null}}, "ImageFieldFile": {".class": "SymbolTableNode", "kind": "Gdef", "node": {".class": "TypeInfo", "_promote": null, "abstract_attributes": [], "bases": ["django.core.files.images.ImageFile", "django.db.models.fields.files.FieldFile"], "declared_metaclass": null, "defn": {".class": "ClassDef", "fullname": "django.db.models.fields.files.ImageFieldFile", "name": "ImageFieldFile", "type_vars": []}, "flags": [], "fullname": "django.db.models.fields.files.ImageFieldFile", "metaclass_type": null, "metadata": {}, "module_name": "django.db.models.fields.files", "mro": ["django.db.models.fields.files.ImageFieldFile", "django.core.files.images.ImageFile", "django.db.models.fields.files.FieldFile", "django.core.files.base.File", "django.core.files.utils.FileProxyMixin", "builtins.object"], "names": {".class": "SymbolTable", "delete": {".class": "SymbolTableNode", "kind": "Mdef", "node": {".class": "FuncDef", "arg_kinds": [0, 1], "arg_names": ["self", "save"], "flags": [], "fullname": "django.db.models.fields.files.ImageFieldFile.delete", "name": "delete", "type": null}}}, "tuple_type": null, "type_vars": [], "typeddict_type": null}}, "ImageFile": {".class": "SymbolTableNode", "cross_ref": "django.core.files.images.ImageFile", "kind": "Gdef"}, "ImageFileDescriptor": {".class": "SymbolTableNode", "kind": "Gdef", "node": {".class": "TypeInfo", "_promote": null, "abstract_attributes": [], "bases": ["django.db.models.fields.files.FileDescriptor"], "declared_metaclass": null, "defn": {".class": "ClassDef", "fullname": "django.db.models.fields.files.ImageFileDescriptor", "name": "ImageFileDescriptor", "type_vars": []}, "flags": [], "fullname": "django.db.models.fields.files.ImageFileDescriptor", "metaclass_type": null, "metadata": {}, "module_name": "django.db.models.fields.files", "mro": ["django.db.models.fields.files.ImageFileDescriptor", "django.db.models.fields.files.FileDescriptor", "django.db.models.query_utils.DeferredAttribute", "builtins.object"], "names": {".class": "SymbolTable", "__set__": {".class": "SymbolTableNode", "kind": "Mdef", "node": {".class": "FuncDef", "arg_kinds": [0, 0, 0], "arg_names": ["self", "instance", "value"], "flags": [], "fullname": "django.db.models.fields.files.ImageFileDescriptor.__set__", "name": "__set__", "type": null}}}, "tuple_type": null, "type_vars": [], "typeddict_type": null}}, "Storage": {".class": "SymbolTableNode", "cross_ref": "django.core.files.storage.Storage", "kind": "Gdef"}, "_": {".class": "SymbolTableNode", "cross_ref": "django.utils.translation.gettext_lazy", "kind": "Gdef"}, "__doc__": {".class": "SymbolTableNode", "kind": "Gdef", "node": {".class": "Var", "flags": ["is_ready"], "fullname": "django.db.models.fields.files.__doc__", "name": "__doc__", "type": "builtins.str"}}, "__file__": {".class": "SymbolTableNode", "kind": "Gdef", "node": {".class": "Var", "flags": ["is_ready"], "fullname": "django.db.models.fields.files.__file__", "name": "__file__", "type": "builtins.str"}}, "__name__": {".class": "SymbolTableNode", "kind": "Gdef", "node": {".class": "Var", "flags": ["is_ready"], "fullname": "django.db.models.fields.files.__name__", "name": "__name__", "type": "builtins.str"}}, "__package__": {".class": "SymbolTableNode", "kind": "Gdef", "node": {".class": "Var", "flags": ["is_ready"], "fullname": "django.db.models.fields.files.__package__", "name": "__package__", "type": "builtins.str"}}, "checks": {".class": "SymbolTableNode", "cross_ref": "django.core.checks", "kind": "Gdef"}, "datetime": {".class": "SymbolTableNode", "cross_ref": "datetime", "kind": "Gdef"}, "default_storage": {".class": "SymbolTableNode", "cross_ref": "django.core.files.storage.default_storage", "kind": "Gdef"}, "forms": {".class": "SymbolTableNode", "cross_ref": "django.forms", "kind": "Gdef"}, "posixpath": {".class": "SymbolTableNode", "cross_ref": "posixpath", "kind": "Gdef"}, "signals": {".class": "SymbolTableNode", "cross_ref": "django.db.models.signals", "kind": "Gdef"}}, "path": "/home/ibrahim/opensrc/django/django/db/models/fields/files.py"}