{"data_mtime": 1597687502, "dep_lines": [1, 2, 3, 1, 1], "dep_prios": [5, 5, 10, 5, 30], "dependencies": ["typing", "concurrent.futures._base", "sys", "builtins", "abc"], "hash": "fbd46becd1cd8b9aea1eadda2772c87591d64341c0918b16ac084da5dcce26ae", "id": "concurrent.futures.thread", "ignore_all": true, "interface_hash": "e0a6f75ec12eedb81e5ccafefebeb894f5b3d649efb4c24fc2ff1999b342e267", "mtime": 1593463042, "options": {"allow_redefinition": false, "allow_untyped_globals": false, "always_false": [], "always_true": [], "bazel": false, "check_untyped_defs": false, "disallow_any_decorated": false, "disallow_any_explicit": false, "disallow_any_expr": false, "disallow_any_generics": false, "disallow_any_unimported": false, "disallow_incomplete_defs": false, "disallow_subclassing_any": false, "disallow_untyped_calls": false, "disallow_untyped_decorators": false, "disallow_untyped_defs": false, "follow_imports": "silent", "follow_imports_for_stubs": false, "ignore_errors": false, "ignore_missing_imports": true, "implicit_reexport": true, "local_partial_types": false, "mypyc": false, "no_implicit_optional": false, "platform": "linux", "plugins": [], "show_none_errors": true, "strict_equality": false, "strict_optional": true, "strict_optional_whitelist": null, "warn_no_return": true, "warn_return_any": false, "warn_unreachable": false, "warn_unused_ignores": false}, "path": "/home/ibrahim/.local/lib/python3.8/site-packages/mypy/typeshed/stdlib/3/concurrent/futures/thread.pyi", "plugin_data": null, "size": 1162, "suppressed": [], "version_id": "0.782"}