{".class": "MypyFile", "_fullname": "django.forms.fields", "is_partial_stub_package": false, "is_stub": false, "names": {".class": "SymbolTable", "BaseTemporalField": {".class": "SymbolTableNode", "kind": "Gdef", "module_public": false, "node": {".class": "TypeInfo", "_promote": null, "abstract_attributes": [], "bases": ["django.forms.fields.Field"], "declared_metaclass": null, "defn": {".class": "ClassDef", "fullname": "django.forms.fields.BaseTemporalField", "name": "BaseTemporalField", "type_vars": []}, "flags": [], "fullname": "django.forms.fields.BaseTemporalField", "metaclass_type": null, "metadata": {}, "module_name": "django.forms.fields", "mro": ["django.forms.fields.BaseTemporalField", "django.forms.fields.Field", "builtins.object"], "names": {".class": "SymbolTable", "__init__": {".class": "SymbolTableNode", "kind": "Mdef", "node": {".class": "FuncDef", "arg_kinds": [0, 5, 4], "arg_names": ["self", "input_formats", "kwargs"], "flags": [], "fullname": "django.forms.fields.BaseTemporalField.__init__", "name": "__init__", "type": null}}, "input_formats": {".class": "SymbolTableNode", "implicit": true, "kind": "Mdef", "node": {".class": "Var", "flags": [], "fullname": "django.forms.fields.BaseTemporalField.input_formats", "name": "input_formats", "type": {".class": "AnyType", "missing_import_name": null, "source_any": null, "type_of_any": 1}}}, "strptime": {".class": "SymbolTableNode", "kind": "Mdef", "node": {".class": "FuncDef", "arg_kinds": [0, 0, 0], "arg_names": ["self", "value", "format"], "flags": [], "fullname": "django.forms.fields.BaseTemporalField.strptime", "name": "strptime", "type": null}}, "to_python": {".class": "SymbolTableNode", "kind": "Mdef", "node": {".class": "FuncDef", "arg_kinds": [0, 0], "arg_names": ["self", "value"], "flags": [], "fullname": "django.forms.fields.BaseTemporalField.to_python", "name": "to_python", "type": null}}}, "tuple_type": null, "type_vars": [], "typeddict_type": null}}, "BooleanField": {".class": "SymbolTableNode", "kind": "Gdef", "node": {".class": "TypeInfo", "_promote": null, "abstract_attributes": [], "bases": ["django.forms.fields.Field"], "declared_metaclass": null, "defn": {".class": "ClassDef", "fullname": "django.forms.fields.BooleanField", "name": "BooleanField", "type_vars": []}, "flags": [], "fullname": "django.forms.fields.BooleanField", "metaclass_type": null, "metadata": {}, "module_name": "django.forms.fields", "mro": ["django.forms.fields.BooleanField", "django.forms.fields.Field", "builtins.object"], "names": {".class": "SymbolTable", "has_changed": {".class": "SymbolTableNode", "kind": "Mdef", "node": {".class": "FuncDef", "arg_kinds": [0, 0, 0], "arg_names": ["self", "initial", "data"], "flags": [], "fullname": "django.forms.fields.BooleanField.has_changed", "name": "has_changed", "type": null}}, "to_python": {".class": "SymbolTableNode", "kind": "Mdef", "node": {".class": "FuncDef", "arg_kinds": [0, 0], "arg_names": ["self", "value"], "flags": [], "fullname": "django.forms.fields.BooleanField.to_python", "name": "to_python", "type": null}}, "validate": {".class": "SymbolTableNode", "kind": "Mdef", "node": {".class": "FuncDef", "arg_kinds": [0, 0], "arg_names": ["self", "value"], "flags": [], "fullname": "django.forms.fields.BooleanField.validate", "name": "validate", "type": null}}, "widget": {".class": "SymbolTableNode", "kind": "Mdef", "node": {".class": "Var", "flags": ["is_initialized_in_class"], "fullname": "django.forms.fields.BooleanField.widget", "name": "widget", "type": null}}}, "tuple_type": null, "type_vars": [], "typeddict_type": null}}, "BoundField": {".class": "SymbolTableNode", "cross_ref": "django.forms.boundfield.BoundField", "kind": "Gdef", "module_public": false}, "BytesIO": {".class": "SymbolTableNode", "cross_ref": "io.BytesIO", "kind": "Gdef", "module_public": false}, "CallableChoiceIterator": {".class": "SymbolTableNode", "kind": "Gdef", "module_public": false, "node": {".class": "TypeInfo", "_promote": null, "abstract_attributes": [], "bases": ["builtins.object"], "declared_metaclass": null, "defn": {".class": "ClassDef", "fullname": "django.forms.fields.CallableChoiceIterator", "name": "CallableChoiceIterator", "type_vars": []}, "flags": [], "fullname": "django.forms.fields.CallableChoiceIterator", "metaclass_type": null, "metadata": {}, "module_name": "django.forms.fields", "mro": ["django.forms.fields.CallableChoiceIterator", "builtins.object"], "names": {".class": "SymbolTable", "__init__": {".class": "SymbolTableNode", "kind": "Mdef", "node": {".class": "FuncDef", "arg_kinds": [0, 0], "arg_names": ["self", "choices_func"], "flags": [], "fullname": "django.forms.fields.CallableChoiceIterator.__init__", "name": "__init__", "type": null}}, "__iter__": {".class": "SymbolTableNode", "kind": "Mdef", "node": {".class": "FuncDef", "arg_kinds": [0], "arg_names": ["self"], "flags": ["is_generator"], "fullname": "django.forms.fields.CallableChoiceIterator.__iter__", "name": "__iter__", "type": null}}, "choices_func": {".class": "SymbolTableNode", "implicit": true, "kind": "Mdef", "node": {".class": "Var", "flags": [], "fullname": "django.forms.fields.CallableChoiceIterator.choices_func", "name": "choices_func", "type": {".class": "AnyType", "missing_import_name": null, "source_any": null, "type_of_any": 1}}}}, "tuple_type": null, "type_vars": [], "typeddict_type": null}}, "CharField": {".class": "SymbolTableNode", "kind": "Gdef", "node": {".class": "TypeInfo", "_promote": null, "abstract_attributes": [], "bases": ["django.forms.fields.Field"], "declared_metaclass": null, "defn": {".class": "ClassDef", "fullname": "django.forms.fields.CharField", "name": "CharField", "type_vars": []}, "flags": [], "fullname": "django.forms.fields.CharField", "metaclass_type": null, "metadata": {}, "module_name": "django.forms.fields", "mro": ["django.forms.fields.CharField", "django.forms.fields.Field", "builtins.object"], "names": {".class": "SymbolTable", "__init__": {".class": "SymbolTableNode", "kind": "Mdef", "node": {".class": "FuncDef", "arg_kinds": [0, 5, 5, 5, 5, 4], "arg_names": ["self", "max_length", "min_length", "strip", "empty_value", "kwargs"], "flags": [], "fullname": "django.forms.fields.CharField.__init__", "name": "__init__", "type": null}}, "empty_value": {".class": "SymbolTableNode", "implicit": true, "kind": "Mdef", "node": {".class": "Var", "flags": [], "fullname": "django.forms.fields.CharField.empty_value", "name": "empty_value", "type": {".class": "AnyType", "missing_import_name": null, "source_any": null, "type_of_any": 1}}}, "max_length": {".class": "SymbolTableNode", "implicit": true, "kind": "Mdef", "node": {".class": "Var", "flags": [], "fullname": "django.forms.fields.CharField.max_length", "name": "max_length", "type": {".class": "AnyType", "missing_import_name": null, "source_any": null, "type_of_any": 1}}}, "min_length": {".class": "SymbolTableNode", "implicit": true, "kind": "Mdef", "node": {".class": "Var", "flags": [], "fullname": "django.forms.fields.CharField.min_length", "name": "min_length", "type": {".class": "AnyType", "missing_import_name": null, "source_any": null, "type_of_any": 1}}}, "strip": {".class": "SymbolTableNode", "implicit": true, "kind": "Mdef", "node": {".class": "Var", "flags": [], "fullname": "django.forms.fields.CharField.strip", "name": "strip", "type": {".class": "AnyType", "missing_import_name": null, "source_any": null, "type_of_any": 1}}}, "to_python": {".class": "SymbolTableNode", "kind": "Mdef", "node": {".class": "FuncDef", "arg_kinds": [0, 0], "arg_names": ["self", "value"], "flags": [], "fullname": "django.forms.fields.CharField.to_python", "name": "to_python", "type": null}}, "widget_attrs": {".class": "SymbolTableNode", "kind": "Mdef", "node": {".class": "FuncDef", "arg_kinds": [0, 0], "arg_names": ["self", "widget"], "flags": [], "fullname": "django.forms.fields.CharField.widget_attrs", "name": "widget_attrs", "type": null}}}, "tuple_type": null, "type_vars": [], "typeddict_type": null}}, "CheckboxInput": {".class": "SymbolTableNode", "cross_ref": "django.forms.widgets.CheckboxInput", "kind": "Gdef", "module_public": false}, "ChoiceField": {".class": "SymbolTableNode", "kind": "Gdef", "node": {".class": "TypeInfo", "_promote": null, "abstract_attributes": [], "bases": ["django.forms.fields.Field"], "declared_metaclass": null, "defn": {".class": "ClassDef", "fullname": "django.forms.fields.ChoiceField", "name": "ChoiceField", "type_vars": []}, "flags": [], "fullname": "django.forms.fields.ChoiceField", "metaclass_type": null, "metadata": {}, "module_name": "django.forms.fields", "mro": ["django.forms.fields.ChoiceField", "django.forms.fields.Field", "builtins.object"], "names": {".class": "SymbolTable", "__deepcopy__": {".class": "SymbolTableNode", "kind": "Mdef", "node": {".class": "FuncDef", "arg_kinds": [0, 0], "arg_names": ["self", "memo"], "flags": [], "fullname": "django.forms.fields.ChoiceField.__deepcopy__", "name": "__deepcopy__", "type": null}}, "__init__": {".class": "SymbolTableNode", "kind": "Mdef", "node": {".class": "FuncDef", "arg_kinds": [0, 5, 4], "arg_names": ["self", "choices", "kwargs"], "flags": [], "fullname": "django.forms.fields.ChoiceField.__init__", "name": "__init__", "type": null}}, "_choices": {".class": "SymbolTableNode", "implicit": true, "kind": "Mdef", "node": {".class": "Var", "flags": [], "fullname": "django.forms.fields.ChoiceField._choices", "name": "_choices", "type": {".class": "AnyType", "missing_import_name": null, "source_any": null, "type_of_any": 1}}}, "_get_choices": {".class": "SymbolTableNode", "kind": "Mdef", "node": {".class": "FuncDef", "arg_kinds": [0], "arg_names": ["self"], "flags": [], "fullname": "django.forms.fields.ChoiceField._get_choices", "name": "_get_choices", "type": null}}, "_set_choices": {".class": "SymbolTableNode", "kind": "Mdef", "node": {".class": "FuncDef", "arg_kinds": [0, 0], "arg_names": ["self", "value"], "flags": [], "fullname": "django.forms.fields.ChoiceField._set_choices", "name": "_set_choices", "type": null}}, "choices": {".class": "SymbolTableNode", "kind": "Mdef", "node": {".class": "Var", "flags": ["is_initialized_in_class"], "fullname": "django.forms.fields.ChoiceField.choices", "name": "choices", "type": "builtins.property"}}, "default_error_messages": {".class": "SymbolTableNode", "kind": "Mdef", "node": {".class": "Var", "flags": ["is_initialized_in_class"], "fullname": "django.forms.fields.ChoiceField.default_error_messages", "name": "default_error_messages", "type": {".class": "Instance", "args": ["builtins.str", {".class": "AnyType", "missing_import_name": null, "source_any": {".class": "AnyType", "missing_import_name": null, "source_any": null, "type_of_any": 1}, "type_of_any": 7}], "type_ref": "builtins.dict"}}}, "to_python": {".class": "SymbolTableNode", "kind": "Mdef", "node": {".class": "FuncDef", "arg_kinds": [0, 0], "arg_names": ["self", "value"], "flags": [], "fullname": "django.forms.fields.ChoiceField.to_python", "name": "to_python", "type": null}}, "valid_value": {".class": "SymbolTableNode", "kind": "Mdef", "node": {".class": "FuncDef", "arg_kinds": [0, 0], "arg_names": ["self", "value"], "flags": [], "fullname": "django.forms.fields.ChoiceField.valid_value", "name": "valid_value", "type": null}}, "validate": {".class": "SymbolTableNode", "kind": "Mdef", "node": {".class": "FuncDef", "arg_kinds": [0, 0], "arg_names": ["self", "value"], "flags": [], "fullname": "django.forms.fields.ChoiceField.validate", "name": "validate", "type": null}}, "widget": {".class": "SymbolTableNode", "kind": "Mdef", "node": {".class": "Var", "flags": ["is_initialized_in_class"], "fullname": "django.forms.fields.ChoiceField.widget", "name": "widget", "type": null}}}, "tuple_type": null, "type_vars": [], "typeddict_type": null}}, "ClearableFileInput": {".class": "SymbolTableNode", "cross_ref": "django.forms.widgets.ClearableFileInput", "kind": "Gdef", "module_public": false}, "ComboField": {".class": "SymbolTableNode", "kind": "Gdef", "node": {".class": "TypeInfo", "_promote": null, "abstract_attributes": [], "bases": ["django.forms.fields.Field"], "declared_metaclass": null, "defn": {".class": "ClassDef", "fullname": "django.forms.fields.ComboField", "name": "ComboField", "type_vars": []}, "flags": [], "fullname": "django.forms.fields.ComboField", "metaclass_type": null, "metadata": {}, "module_name": "django.forms.fields", "mro": ["django.forms.fields.ComboField", "django.forms.fields.Field", "builtins.object"], "names": {".class": "SymbolTable", "__init__": {".class": "SymbolTableNode", "kind": "Mdef", "node": {".class": "FuncDef", "arg_kinds": [0, 0, 4], "arg_names": ["self", "fields", "kwargs"], "flags": [], "fullname": "django.forms.fields.ComboField.__init__", "name": "__init__", "type": null}}, "clean": {".class": "SymbolTableNode", "kind": "Mdef", "node": {".class": "FuncDef", "arg_kinds": [0, 0], "arg_names": ["self", "value"], "flags": [], "fullname": "django.forms.fields.ComboField.clean", "name": "clean", "type": null}}, "fields": {".class": "SymbolTableNode", "implicit": true, "kind": "Mdef", "node": {".class": "Var", "flags": [], "fullname": "django.forms.fields.ComboField.fields", "name": "fields", "type": {".class": "AnyType", "missing_import_name": null, "source_any": null, "type_of_any": 1}}}}, "tuple_type": null, "type_vars": [], "typeddict_type": null}}, "DateField": {".class": "SymbolTableNode", "kind": "Gdef", "node": {".class": "TypeInfo", "_promote": null, "abstract_attributes": [], "bases": ["django.forms.fields.BaseTemporalField"], "declared_metaclass": null, "defn": {".class": "ClassDef", "fullname": "django.forms.fields.DateField", "name": "DateField", "type_vars": []}, "flags": [], "fullname": "django.forms.fields.DateField", "metaclass_type": null, "metadata": {}, "module_name": "django.forms.fields", "mro": ["django.forms.fields.DateField", "django.forms.fields.BaseTemporalField", "django.forms.fields.Field", "builtins.object"], "names": {".class": "SymbolTable", "default_error_messages": {".class": "SymbolTableNode", "kind": "Mdef", "node": {".class": "Var", "flags": ["is_initialized_in_class"], "fullname": "django.forms.fields.DateField.default_error_messages", "name": "default_error_messages", "type": {".class": "Instance", "args": ["builtins.str", {".class": "AnyType", "missing_import_name": null, "source_any": {".class": "AnyType", "missing_import_name": null, "source_any": null, "type_of_any": 1}, "type_of_any": 7}], "type_ref": "builtins.dict"}}}, "input_formats": {".class": "SymbolTableNode", "kind": "Mdef", "node": {".class": "Var", "flags": ["is_initialized_in_class"], "fullname": "django.forms.fields.DateField.input_formats", "name": "input_formats", "type": {".class": "AnyType", "missing_import_name": null, "source_any": {".class": "AnyType", "missing_import_name": null, "source_any": null, "type_of_any": 1}, "type_of_any": 7}}}, "strptime": {".class": "SymbolTableNode", "kind": "Mdef", "node": {".class": "FuncDef", "arg_kinds": [0, 0, 0], "arg_names": ["self", "value", "format"], "flags": [], "fullname": "django.forms.fields.DateField.strptime", "name": "strptime", "type": null}}, "to_python": {".class": "SymbolTableNode", "kind": "Mdef", "node": {".class": "FuncDef", "arg_kinds": [0, 0], "arg_names": ["self", "value"], "flags": [], "fullname": "django.forms.fields.DateField.to_python", "name": "to_python", "type": null}}, "widget": {".class": "SymbolTableNode", "kind": "Mdef", "node": {".class": "Var", "flags": ["is_initialized_in_class"], "fullname": "django.forms.fields.DateField.widget", "name": "widget", "type": {".class": "CallableType", "arg_kinds": [1, 1], "arg_names": ["attrs", "format"], "arg_types": [{".class": "AnyType", "missing_import_name": null, "source_any": null, "type_of_any": 1}, {".class": "AnyType", "missing_import_name": null, "source_any": null, "type_of_any": 1}], "bound_args": ["django.forms.widgets.DateInput"], "def_extras": {}, "fallback": "django.forms.widgets.MediaDefiningClass", "implicit": true, "is_ellipsis_args": false, "name": null, "ret_type": "django.forms.widgets.DateInput", "variables": []}}}}, "tuple_type": null, "type_vars": [], "typeddict_type": null}}, "DateInput": {".class": "SymbolTableNode", "cross_ref": "django.forms.widgets.DateInput", "kind": "Gdef", "module_public": false}, "DateTimeField": {".class": "SymbolTableNode", "kind": "Gdef", "node": {".class": "TypeInfo", "_promote": null, "abstract_attributes": [], "bases": ["django.forms.fields.BaseTemporalField"], "declared_metaclass": null, "defn": {".class": "ClassDef", "fullname": "django.forms.fields.DateTimeField", "name": "DateTimeField", "type_vars": []}, "flags": [], "fullname": "django.forms.fields.DateTimeField", "metaclass_type": null, "metadata": {}, "module_name": "django.forms.fields", "mro": ["django.forms.fields.DateTimeField", "django.forms.fields.BaseTemporalField", "django.forms.fields.Field", "builtins.object"], "names": {".class": "SymbolTable", "default_error_messages": {".class": "SymbolTableNode", "kind": "Mdef", "node": {".class": "Var", "flags": ["is_initialized_in_class"], "fullname": "django.forms.fields.DateTimeField.default_error_messages", "name": "default_error_messages", "type": {".class": "Instance", "args": ["builtins.str", {".class": "AnyType", "missing_import_name": null, "source_any": {".class": "AnyType", "missing_import_name": null, "source_any": null, "type_of_any": 1}, "type_of_any": 7}], "type_ref": "builtins.dict"}}}, "input_formats": {".class": "SymbolTableNode", "kind": "Mdef", "node": {".class": "Var", "flags": ["is_initialized_in_class"], "fullname": "django.forms.fields.DateTimeField.input_formats", "name": "input_formats", "type": "django.forms.fields.DateTimeFormatsIterator"}}, "prepare_value": {".class": "SymbolTableNode", "kind": "Mdef", "node": {".class": "FuncDef", "arg_kinds": [0, 0], "arg_names": ["self", "value"], "flags": [], "fullname": "django.forms.fields.DateTimeField.prepare_value", "name": "prepare_value", "type": null}}, "strptime": {".class": "SymbolTableNode", "kind": "Mdef", "node": {".class": "FuncDef", "arg_kinds": [0, 0, 0], "arg_names": ["self", "value", "format"], "flags": [], "fullname": "django.forms.fields.DateTimeField.strptime", "name": "strptime", "type": null}}, "to_python": {".class": "SymbolTableNode", "kind": "Mdef", "node": {".class": "FuncDef", "arg_kinds": [0, 0], "arg_names": ["self", "value"], "flags": [], "fullname": "django.forms.fields.DateTimeField.to_python", "name": "to_python", "type": null}}, "widget": {".class": "SymbolTableNode", "kind": "Mdef", "node": {".class": "Var", "flags": ["is_initialized_in_class"], "fullname": "django.forms.fields.DateTimeField.widget", "name": "widget", "type": {".class": "CallableType", "arg_kinds": [1, 1], "arg_names": ["attrs", "format"], "arg_types": [{".class": "AnyType", "missing_import_name": null, "source_any": null, "type_of_any": 1}, {".class": "AnyType", "missing_import_name": null, "source_any": null, "type_of_any": 1}], "bound_args": ["django.forms.widgets.DateTimeInput"], "def_extras": {}, "fallback": "django.forms.widgets.MediaDefiningClass", "implicit": true, "is_ellipsis_args": false, "name": null, "ret_type": "django.forms.widgets.DateTimeInput", "variables": []}}}}, "tuple_type": null, "type_vars": [], "typeddict_type": null}}, "DateTimeFormatsIterator": {".class": "SymbolTableNode", "kind": "Gdef", "module_public": false, "node": {".class": "TypeInfo", "_promote": null, "abstract_attributes": [], "bases": ["builtins.object"], "declared_metaclass": null, "defn": {".class": "ClassDef", "fullname": "django.forms.fields.DateTimeFormatsIterator", "name": "DateTimeFormatsIterator", "type_vars": []}, "flags": [], "fullname": "django.forms.fields.DateTimeFormatsIterator", "metaclass_type": null, "metadata": {}, "module_name": "django.forms.fields", "mro": ["django.forms.fields.DateTimeFormatsIterator", "builtins.object"], "names": {".class": "SymbolTable", "__iter__": {".class": "SymbolTableNode", "kind": "Mdef", "node": {".class": "FuncDef", "arg_kinds": [0], "arg_names": ["self"], "flags": ["is_generator"], "fullname": "django.forms.fields.DateTimeFormatsIterator.__iter__", "name": "__iter__", "type": null}}}, "tuple_type": null, "type_vars": [], "typeddict_type": null}}, "DateTimeInput": {".class": "SymbolTableNode", "cross_ref": "django.forms.widgets.DateTimeInput", "kind": "Gdef", "module_public": false}, "Decimal": {".class": "SymbolTableNode", "cross_ref": "decimal.Decimal", "kind": "Gdef", "module_public": false}, "DecimalException": {".class": "SymbolTableNode", "cross_ref": "decimal.DecimalException", "kind": "Gdef", "module_public": false}, "DecimalField": {".class": "SymbolTableNode", "kind": "Gdef", "node": {".class": "TypeInfo", "_promote": null, "abstract_attributes": [], "bases": ["django.forms.fields.IntegerField"], "declared_metaclass": null, "defn": {".class": "ClassDef", "fullname": "django.forms.fields.DecimalField", "name": "DecimalField", "type_vars": []}, "flags": [], "fullname": "django.forms.fields.DecimalField", "metaclass_type": null, "metadata": {}, "module_name": "django.forms.fields", "mro": ["django.forms.fields.DecimalField", "django.forms.fields.IntegerField", "django.forms.fields.Field", "builtins.object"], "names": {".class": "SymbolTable", "__init__": {".class": "SymbolTableNode", "kind": "Mdef", "node": {".class": "FuncDef", "arg_kinds": [0, 5, 5, 5, 5, 4], "arg_names": ["self", "max_value", "min_value", "max_digits", "decimal_places", "kwargs"], "flags": [], "fullname": "django.forms.fields.DecimalField.__init__", "name": "__init__", "type": null}}, "decimal_places": {".class": "SymbolTableNode", "implicit": true, "kind": "Mdef", "node": {".class": "Var", "flags": [], "fullname": "django.forms.fields.DecimalField.decimal_places", "name": "decimal_places", "type": {".class": "AnyType", "missing_import_name": null, "source_any": null, "type_of_any": 1}}}, "default_error_messages": {".class": "SymbolTableNode", "kind": "Mdef", "node": {".class": "Var", "flags": ["is_initialized_in_class"], "fullname": "django.forms.fields.DecimalField.default_error_messages", "name": "default_error_messages", "type": {".class": "Instance", "args": ["builtins.str", {".class": "AnyType", "missing_import_name": null, "source_any": {".class": "AnyType", "missing_import_name": null, "source_any": null, "type_of_any": 1}, "type_of_any": 7}], "type_ref": "builtins.dict"}}}, "max_digits": {".class": "SymbolTableNode", "implicit": true, "kind": "Mdef", "node": {".class": "Var", "flags": [], "fullname": "django.forms.fields.DecimalField.max_digits", "name": "max_digits", "type": {".class": "AnyType", "missing_import_name": null, "source_any": null, "type_of_any": 1}}}, "to_python": {".class": "SymbolTableNode", "kind": "Mdef", "node": {".class": "FuncDef", "arg_kinds": [0, 0], "arg_names": ["self", "value"], "flags": [], "fullname": "django.forms.fields.DecimalField.to_python", "name": "to_python", "type": null}}, "widget_attrs": {".class": "SymbolTableNode", "kind": "Mdef", "node": {".class": "FuncDef", "arg_kinds": [0, 0], "arg_names": ["self", "widget"], "flags": [], "fullname": "django.forms.fields.DecimalField.widget_attrs", "name": "widget_attrs", "type": null}}}, "tuple_type": null, "type_vars": [], "typeddict_type": null}}, "DurationField": {".class": "SymbolTableNode", "kind": "Gdef", "node": {".class": "TypeInfo", "_promote": null, "abstract_attributes": [], "bases": ["django.forms.fields.Field"], "declared_metaclass": null, "defn": {".class": "ClassDef", "fullname": "django.forms.fields.DurationField", "name": "DurationField", "type_vars": []}, "flags": [], "fullname": "django.forms.fields.DurationField", "metaclass_type": null, "metadata": {}, "module_name": "django.forms.fields", "mro": ["django.forms.fields.DurationField", "django.forms.fields.Field", "builtins.object"], "names": {".class": "SymbolTable", "default_error_messages": {".class": "SymbolTableNode", "kind": "Mdef", "node": {".class": "Var", "flags": ["is_initialized_in_class"], "fullname": "django.forms.fields.DurationField.default_error_messages", "name": "default_error_messages", "type": {".class": "Instance", "args": ["builtins.str", {".class": "AnyType", "missing_import_name": null, "source_any": {".class": "AnyType", "missing_import_name": null, "source_any": null, "type_of_any": 1}, "type_of_any": 7}], "type_ref": "builtins.dict"}}}, "prepare_value": {".class": "SymbolTableNode", "kind": "Mdef", "node": {".class": "FuncDef", "arg_kinds": [0, 0], "arg_names": ["self", "value"], "flags": [], "fullname": "django.forms.fields.DurationField.prepare_value", "name": "prepare_value", "type": null}}, "to_python": {".class": "SymbolTableNode", "kind": "Mdef", "node": {".class": "FuncDef", "arg_kinds": [0, 0], "arg_names": ["self", "value"], "flags": [], "fullname": "django.forms.fields.DurationField.to_python", "name": "to_python", "type": null}}}, "tuple_type": null, "type_vars": [], "typeddict_type": null}}, "EmailField": {".class": "SymbolTableNode", "kind": "Gdef", "node": {".class": "TypeInfo", "_promote": null, "abstract_attributes": [], "bases": ["django.forms.fields.CharField"], "declared_metaclass": null, "defn": {".class": "ClassDef", "fullname": "django.forms.fields.EmailField", "name": "EmailField", "type_vars": []}, "flags": [], "fullname": "django.forms.fields.EmailField", "metaclass_type": null, "metadata": {}, "module_name": "django.forms.fields", "mro": ["django.forms.fields.EmailField", "django.forms.fields.CharField", "django.forms.fields.Field", "builtins.object"], "names": {".class": "SymbolTable", "__init__": {".class": "SymbolTableNode", "kind": "Mdef", "node": {".class": "FuncDef", "arg_kinds": [0, 4], "arg_names": ["self", "kwargs"], "flags": [], "fullname": "django.forms.fields.EmailField.__init__", "name": "__init__", "type": null}}, "default_validators": {".class": "SymbolTableNode", "kind": "Mdef", "node": {".class": "Var", "flags": ["is_initialized_in_class"], "fullname": "django.forms.fields.EmailField.default_validators", "name": "default_validators", "type": {".class": "Instance", "args": ["django.core.validators.EmailValidator"], "type_ref": "builtins.list"}}}, "widget": {".class": "SymbolTableNode", "kind": "Mdef", "node": {".class": "Var", "flags": ["is_initialized_in_class"], "fullname": "django.forms.fields.EmailField.widget", "name": "widget", "type": null}}}, "tuple_type": null, "type_vars": [], "typeddict_type": null}}, "EmailInput": {".class": "SymbolTableNode", "cross_ref": "django.forms.widgets.EmailInput", "kind": "Gdef", "module_public": false}, "FILE_INPUT_CONTRADICTION": {".class": "SymbolTableNode", "cross_ref": "django.forms.widgets.FILE_INPUT_CONTRADICTION", "kind": "Gdef", "module_public": false}, "Field": {".class": "SymbolTableNode", "kind": "Gdef", "node": {".class": "TypeInfo", "_promote": null, "abstract_attributes": [], "bases": ["builtins.object"], "declared_metaclass": null, "defn": {".class": "ClassDef", "fullname": "django.forms.fields.Field", "name": "Field", "type_vars": []}, "flags": [], "fullname": "django.forms.fields.Field", "metaclass_type": null, "metadata": {}, "module_name": "django.forms.fields", "mro": ["django.forms.fields.Field", "builtins.object"], "names": {".class": "SymbolTable", "__deepcopy__": {".class": "SymbolTableNode", "kind": "Mdef", "node": {".class": "FuncDef", "arg_kinds": [0, 0], "arg_names": ["self", "memo"], "flags": [], "fullname": "django.forms.fields.Field.__deepcopy__", "name": "__deepcopy__", "type": null}}, "__init__": {".class": "SymbolTableNode", "kind": "Mdef", "node": {".class": "FuncDef", "arg_kinds": [0, 5, 5, 5, 5, 5, 5, 5, 5, 5, 5, 5], "arg_names": ["self", "required", "widget", "label", "initial", "help_text", "error_messages", "show_hidden_initial", "validators", "localize", "disabled", "label_suffix"], "flags": [], "fullname": "django.forms.fields.Field.__init__", "name": "__init__", "type": null}}, "bound_data": {".class": "SymbolTableNode", "kind": "Mdef", "node": {".class": "FuncDef", "arg_kinds": [0, 0, 0], "arg_names": ["self", "data", "initial"], "flags": [], "fullname": "django.forms.fields.Field.bound_data", "name": "bound_data", "type": null}}, "clean": {".class": "SymbolTableNode", "kind": "Mdef", "node": {".class": "FuncDef", "arg_kinds": [0, 0], "arg_names": ["self", "value"], "flags": [], "fullname": "django.forms.fields.Field.clean", "name": "clean", "type": null}}, "default_error_messages": {".class": "SymbolTableNode", "kind": "Mdef", "node": {".class": "Var", "flags": ["is_initialized_in_class"], "fullname": "django.forms.fields.Field.default_error_messages", "name": "default_error_messages", "type": {".class": "Instance", "args": ["builtins.str", {".class": "AnyType", "missing_import_name": null, "source_any": {".class": "AnyType", "missing_import_name": null, "source_any": null, "type_of_any": 1}, "type_of_any": 7}], "type_ref": "builtins.dict"}}}, "default_validators": {".class": "SymbolTableNode", "kind": "Mdef", "node": {".class": "Var", "flags": ["is_initialized_in_class"], "fullname": "django.forms.fields.Field.default_validators", "name": "default_validators", "type": {".class": "Instance", "args": [{".class": "AnyType", "missing_import_name": null, "source_any": null, "type_of_any": 1}], "type_ref": "builtins.list"}}}, "disabled": {".class": "SymbolTableNode", "implicit": true, "kind": "Mdef", "node": {".class": "Var", "flags": [], "fullname": "django.forms.fields.Field.disabled", "name": "disabled", "type": {".class": "AnyType", "missing_import_name": null, "source_any": null, "type_of_any": 1}}}, "empty_values": {".class": "SymbolTableNode", "kind": "Mdef", "node": {".class": "Var", "flags": ["is_initialized_in_class"], "fullname": "django.forms.fields.Field.empty_values", "name": "empty_values", "type": {".class": "Instance", "args": [{".class": "UnionType", "items": [{".class": "Instance", "args": [{".class": "AnyType", "missing_import_name": null, "source_any": null, "type_of_any": 5}, {".class": "AnyType", "missing_import_name": null, "source_any": null, "type_of_any": 5}], "type_ref": "builtins.dict"}, {".class": "TupleType", "implicit": false, "items": [], "partial_fallback": {".class": "Instance", "args": [{".class": "AnyType", "missing_import_name": null, "source_any": null, "type_of_any": 6}], "type_ref": "builtins.tuple"}}, {".class": "Instance", "args": [{".class": "AnyType", "missing_import_name": null, "source_any": null, "type_of_any": 5}], "type_ref": "builtins.list"}, "builtins.str", {".class": "NoneType"}]}], "type_ref": "builtins.list"}}}, "error_messages": {".class": "SymbolTableNode", "implicit": true, "kind": "Mdef", "node": {".class": "Var", "flags": [], "fullname": "django.forms.fields.Field.error_messages", "name": "error_messages", "type": {".class": "AnyType", "missing_import_name": null, "source_any": null, "type_of_any": 1}}}, "get_bound_field": {".class": "SymbolTableNode", "kind": "Mdef", "node": {".class": "FuncDef", "arg_kinds": [0, 0, 0], "arg_names": ["self", "form", "field_name"], "flags": [], "fullname": "django.forms.fields.Field.get_bound_field", "name": "get_bound_field", "type": null}}, "has_changed": {".class": "SymbolTableNode", "kind": "Mdef", "node": {".class": "FuncDef", "arg_kinds": [0, 0, 0], "arg_names": ["self", "initial", "data"], "flags": [], "fullname": "django.forms.fields.Field.has_changed", "name": "has_changed", "type": null}}, "help_text": {".class": "SymbolTableNode", "implicit": true, "kind": "Mdef", "node": {".class": "Var", "flags": [], "fullname": "django.forms.fields.Field.help_text", "name": "help_text", "type": {".class": "AnyType", "missing_import_name": null, "source_any": null, "type_of_any": 1}}}, "hidden_widget": {".class": "SymbolTableNode", "kind": "Mdef", "node": {".class": "Var", "flags": ["is_initialized_in_class"], "fullname": "django.forms.fields.Field.hidden_widget", "name": "hidden_widget", "type": {".class": "CallableType", "arg_kinds": [1], "arg_names": ["attrs"], "arg_types": [{".class": "AnyType", "missing_import_name": null, "source_any": null, "type_of_any": 1}], "bound_args": ["django.forms.widgets.HiddenInput"], "def_extras": {}, "fallback": "django.forms.widgets.MediaDefiningClass", "implicit": true, "is_ellipsis_args": false, "name": null, "ret_type": "django.forms.widgets.HiddenInput", "variables": []}}}, "initial": {".class": "SymbolTableNode", "implicit": true, "kind": "Mdef", "node": {".class": "Var", "flags": [], "fullname": "django.forms.fields.Field.initial", "name": "initial", "type": {".class": "AnyType", "missing_import_name": null, "source_any": null, "type_of_any": 1}}}, "label": {".class": "SymbolTableNode", "implicit": true, "kind": "Mdef", "node": {".class": "Var", "flags": [], "fullname": "django.forms.fields.Field.label", "name": "label", "type": {".class": "AnyType", "missing_import_name": null, "source_any": null, "type_of_any": 1}}}, "label_suffix": {".class": "SymbolTableNode", "implicit": true, "kind": "Mdef", "node": {".class": "Var", "flags": [], "fullname": "django.forms.fields.Field.label_suffix", "name": "label_suffix", "type": {".class": "AnyType", "missing_import_name": null, "source_any": null, "type_of_any": 1}}}, "localize": {".class": "SymbolTableNode", "implicit": true, "kind": "Mdef", "node": {".class": "Var", "flags": [], "fullname": "django.forms.fields.Field.localize", "name": "localize", "type": {".class": "AnyType", "missing_import_name": null, "source_any": null, "type_of_any": 1}}}, "prepare_value": {".class": "SymbolTableNode", "kind": "Mdef", "node": {".class": "FuncDef", "arg_kinds": [0, 0], "arg_names": ["self", "value"], "flags": [], "fullname": "django.forms.fields.Field.prepare_value", "name": "prepare_value", "type": null}}, "required": {".class": "SymbolTableNode", "implicit": true, "kind": "Mdef", "node": {".class": "Var", "flags": [], "fullname": "django.forms.fields.Field.required", "name": "required", "type": {".class": "AnyType", "missing_import_name": null, "source_any": null, "type_of_any": 1}}}, "run_validators": {".class": "SymbolTableNode", "kind": "Mdef", "node": {".class": "FuncDef", "arg_kinds": [0, 0], "arg_names": ["self", "value"], "flags": [], "fullname": "django.forms.fields.Field.run_validators", "name": "run_validators", "type": null}}, "show_hidden_initial": {".class": "SymbolTableNode", "implicit": true, "kind": "Mdef", "node": {".class": "Var", "flags": [], "fullname": "django.forms.fields.Field.show_hidden_initial", "name": "show_hidden_initial", "type": {".class": "AnyType", "missing_import_name": null, "source_any": null, "type_of_any": 1}}}, "to_python": {".class": "SymbolTableNode", "kind": "Mdef", "node": {".class": "FuncDef", "arg_kinds": [0, 0], "arg_names": ["self", "value"], "flags": [], "fullname": "django.forms.fields.Field.to_python", "name": "to_python", "type": null}}, "validate": {".class": "SymbolTableNode", "kind": "Mdef", "node": {".class": "FuncDef", "arg_kinds": [0, 0], "arg_names": ["self", "value"], "flags": [], "fullname": "django.forms.fields.Field.validate", "name": "validate", "type": null}}, "validators": {".class": "SymbolTableNode", "implicit": true, "kind": "Mdef", "node": {".class": "Var", "flags": [], "fullname": "django.forms.fields.Field.validators", "name": "validators", "type": {".class": "AnyType", "missing_import_name": null, "source_any": null, "type_of_any": 1}}}, "widget": {".class": "SymbolTableNode", "kind": "Mdef", "node": {".class": "Var", "flags": ["is_initialized_in_class"], "fullname": "django.forms.fields.Field.widget", "name": "widget", "type": {".class": "CallableType", "arg_kinds": [1], "arg_names": ["attrs"], "arg_types": [{".class": "AnyType", "missing_import_name": null, "source_any": null, "type_of_any": 1}], "bound_args": ["django.forms.widgets.TextInput"], "def_extras": {}, "fallback": "django.forms.widgets.MediaDefiningClass", "implicit": true, "is_ellipsis_args": false, "name": null, "ret_type": "django.forms.widgets.TextInput", "variables": []}}}, "widget_attrs": {".class": "SymbolTableNode", "kind": "Mdef", "node": {".class": "FuncDef", "arg_kinds": [0, 0], "arg_names": ["self", "widget"], "flags": [], "fullname": "django.forms.fields.Field.widget_attrs", "name": "widget_attrs", "type": null}}}, "tuple_type": null, "type_vars": [], "typeddict_type": null}}, "FileField": {".class": "SymbolTableNode", "kind": "Gdef", "node": {".class": "TypeInfo", "_promote": null, "abstract_attributes": [], "bases": ["django.forms.fields.Field"], "declared_metaclass": null, "defn": {".class": "ClassDef", "fullname": "django.forms.fields.FileField", "name": "FileField", "type_vars": []}, "flags": [], "fullname": "django.forms.fields.FileField", "metaclass_type": null, "metadata": {}, "module_name": "django.forms.fields", "mro": ["django.forms.fields.FileField", "django.forms.fields.Field", "builtins.object"], "names": {".class": "SymbolTable", "__init__": {".class": "SymbolTableNode", "kind": "Mdef", "node": {".class": "FuncDef", "arg_kinds": [0, 5, 5, 4], "arg_names": ["self", "max_length", "allow_empty_file", "kwargs"], "flags": [], "fullname": "django.forms.fields.FileField.__init__", "name": "__init__", "type": null}}, "allow_empty_file": {".class": "SymbolTableNode", "implicit": true, "kind": "Mdef", "node": {".class": "Var", "flags": [], "fullname": "django.forms.fields.FileField.allow_empty_file", "name": "allow_empty_file", "type": {".class": "AnyType", "missing_import_name": null, "source_any": null, "type_of_any": 1}}}, "bound_data": {".class": "SymbolTableNode", "kind": "Mdef", "node": {".class": "FuncDef", "arg_kinds": [0, 0, 0], "arg_names": ["self", "data", "initial"], "flags": [], "fullname": "django.forms.fields.FileField.bound_data", "name": "bound_data", "type": null}}, "clean": {".class": "SymbolTableNode", "kind": "Mdef", "node": {".class": "FuncDef", "arg_kinds": [0, 0, 1], "arg_names": ["self", "data", "initial"], "flags": [], "fullname": "django.forms.fields.FileField.clean", "name": "clean", "type": null}}, "default_error_messages": {".class": "SymbolTableNode", "kind": "Mdef", "node": {".class": "Var", "flags": ["is_initialized_in_class"], "fullname": "django.forms.fields.FileField.default_error_messages", "name": "default_error_messages", "type": {".class": "Instance", "args": ["builtins.str", {".class": "AnyType", "missing_import_name": null, "source_any": {".class": "AnyType", "missing_import_name": null, "source_any": null, "type_of_any": 1}, "type_of_any": 7}], "type_ref": "builtins.dict"}}}, "has_changed": {".class": "SymbolTableNode", "kind": "Mdef", "node": {".class": "FuncDef", "arg_kinds": [0, 0, 0], "arg_names": ["self", "initial", "data"], "flags": [], "fullname": "django.forms.fields.FileField.has_changed", "name": "has_changed", "type": null}}, "max_length": {".class": "SymbolTableNode", "implicit": true, "kind": "Mdef", "node": {".class": "Var", "flags": [], "fullname": "django.forms.fields.FileField.max_length", "name": "max_length", "type": {".class": "AnyType", "missing_import_name": null, "source_any": null, "type_of_any": 1}}}, "to_python": {".class": "SymbolTableNode", "kind": "Mdef", "node": {".class": "FuncDef", "arg_kinds": [0, 0], "arg_names": ["self", "data"], "flags": [], "fullname": "django.forms.fields.FileField.to_python", "name": "to_python", "type": null}}, "widget": {".class": "SymbolTableNode", "kind": "Mdef", "node": {".class": "Var", "flags": ["is_initialized_in_class"], "fullname": "django.forms.fields.FileField.widget", "name": "widget", "type": null}}}, "tuple_type": null, "type_vars": [], "typeddict_type": null}}, "FileInput": {".class": "SymbolTableNode", "cross_ref": "django.forms.widgets.FileInput", "kind": "Gdef", "module_public": false}, "FilePathField": {".class": "SymbolTableNode", "kind": "Gdef", "node": {".class": "TypeInfo", "_promote": null, "abstract_attributes": [], "bases": ["django.forms.fields.ChoiceField"], "declared_metaclass": null, "defn": {".class": "ClassDef", "fullname": "django.forms.fields.FilePathField", "name": "FilePathField", "type_vars": []}, "flags": [], "fullname": "django.forms.fields.FilePathField", "metaclass_type": null, "metadata": {}, "module_name": "django.forms.fields", "mro": ["django.forms.fields.FilePathField", "django.forms.fields.ChoiceField", "django.forms.fields.Field", "builtins.object"], "names": {".class": "SymbolTable", "__init__": {".class": "SymbolTableNode", "kind": "Mdef", "node": {".class": "FuncDef", "arg_kinds": [0, 0, 5, 5, 5, 5, 4], "arg_names": ["self", "path", "match", "recursive", "allow_files", "allow_folders", "kwargs"], "flags": [], "fullname": "django.forms.fields.FilePathField.__init__", "name": "__init__", "type": null}}, "allow_files": {".class": "SymbolTableNode", "implicit": true, "kind": "Mdef", "node": {".class": "Var", "flags": [], "fullname": "django.forms.fields.FilePathField.allow_files", "name": "allow_files", "type": {".class": "AnyType", "missing_import_name": null, "source_any": null, "type_of_any": 1}}}, "allow_folders": {".class": "SymbolTableNode", "implicit": true, "kind": "Mdef", "node": {".class": "Var", "flags": [], "fullname": "django.forms.fields.FilePathField.allow_folders", "name": "allow_folders", "type": {".class": "AnyType", "missing_import_name": null, "source_any": null, "type_of_any": 1}}}, "match": {".class": "SymbolTableNode", "implicit": true, "kind": "Mdef", "node": {".class": "Var", "flags": [], "fullname": "django.forms.fields.FilePathField.match", "name": "match", "type": {".class": "AnyType", "missing_import_name": null, "source_any": null, "type_of_any": 1}}}, "match_re": {".class": "SymbolTableNode", "implicit": true, "kind": "Mdef", "node": {".class": "Var", "flags": [], "fullname": "django.forms.fields.FilePathField.match_re", "name": "match_re", "type": {".class": "AnyType", "missing_import_name": null, "source_any": null, "type_of_any": 1}}}, "path": {".class": "SymbolTableNode", "implicit": true, "kind": "Mdef", "node": {".class": "Var", "flags": [], "fullname": "django.forms.fields.FilePathField.path", "name": "path", "type": {".class": "AnyType", "missing_import_name": null, "source_any": null, "type_of_any": 1}}}, "recursive": {".class": "SymbolTableNode", "implicit": true, "kind": "Mdef", "node": {".class": "Var", "flags": [], "fullname": "django.forms.fields.FilePathField.recursive", "name": "recursive", "type": {".class": "AnyType", "missing_import_name": null, "source_any": null, "type_of_any": 1}}}}, "tuple_type": null, "type_vars": [], "typeddict_type": null}}, "FloatField": {".class": "SymbolTableNode", "kind": "Gdef", "node": {".class": "TypeInfo", "_promote": null, "abstract_attributes": [], "bases": ["django.forms.fields.IntegerField"], "declared_metaclass": null, "defn": {".class": "ClassDef", "fullname": "django.forms.fields.FloatField", "name": "FloatField", "type_vars": []}, "flags": [], "fullname": "django.forms.fields.FloatField", "metaclass_type": null, "metadata": {}, "module_name": "django.forms.fields", "mro": ["django.forms.fields.FloatField", "django.forms.fields.IntegerField", "django.forms.fields.Field", "builtins.object"], "names": {".class": "SymbolTable", "default_error_messages": {".class": "SymbolTableNode", "kind": "Mdef", "node": {".class": "Var", "flags": ["is_initialized_in_class"], "fullname": "django.forms.fields.FloatField.default_error_messages", "name": "default_error_messages", "type": {".class": "Instance", "args": ["builtins.str", {".class": "AnyType", "missing_import_name": null, "source_any": {".class": "AnyType", "missing_import_name": null, "source_any": null, "type_of_any": 1}, "type_of_any": 7}], "type_ref": "builtins.dict"}}}, "to_python": {".class": "SymbolTableNode", "kind": "Mdef", "node": {".class": "FuncDef", "arg_kinds": [0, 0], "arg_names": ["self", "value"], "flags": [], "fullname": "django.forms.fields.FloatField.to_python", "name": "to_python", "type": null}}, "validate": {".class": "SymbolTableNode", "kind": "Mdef", "node": {".class": "FuncDef", "arg_kinds": [0, 0], "arg_names": ["self", "value"], "flags": [], "fullname": "django.forms.fields.FloatField.validate", "name": "validate", "type": null}}, "widget_attrs": {".class": "SymbolTableNode", "kind": "Mdef", "node": {".class": "FuncDef", "arg_kinds": [0, 0], "arg_names": ["self", "widget"], "flags": [], "fullname": "django.forms.fields.FloatField.widget_attrs", "name": "widget_attrs", "type": null}}}, "tuple_type": null, "type_vars": [], "typeddict_type": null}}, "GenericIPAddressField": {".class": "SymbolTableNode", "kind": "Gdef", "node": {".class": "TypeInfo", "_promote": null, "abstract_attributes": [], "bases": ["django.forms.fields.CharField"], "declared_metaclass": null, "defn": {".class": "ClassDef", "fullname": "django.forms.fields.GenericIPAddressField", "name": "GenericIPAddressField", "type_vars": []}, "flags": [], "fullname": "django.forms.fields.GenericIPAddressField", "metaclass_type": null, "metadata": {}, "module_name": "django.forms.fields", "mro": ["django.forms.fields.GenericIPAddressField", "django.forms.fields.CharField", "django.forms.fields.Field", "builtins.object"], "names": {".class": "SymbolTable", "__init__": {".class": "SymbolTableNode", "kind": "Mdef", "node": {".class": "FuncDef", "arg_kinds": [0, 5, 5, 4], "arg_names": ["self", "protocol", "unpack_ipv4", "kwargs"], "flags": [], "fullname": "django.forms.fields.GenericIPAddressField.__init__", "name": "__init__", "type": null}}, "to_python": {".class": "SymbolTableNode", "kind": "Mdef", "node": {".class": "FuncDef", "arg_kinds": [0, 0], "arg_names": ["self", "value"], "flags": [], "fullname": "django.forms.fields.GenericIPAddressField.to_python", "name": "to_python", "type": null}}, "unpack_ipv4": {".class": "SymbolTableNode", "implicit": true, "kind": "Mdef", "node": {".class": "Var", "flags": [], "fullname": "django.forms.fields.GenericIPAddressField.unpack_ipv4", "name": "unpack_ipv4", "type": {".class": "AnyType", "missing_import_name": null, "source_any": null, "type_of_any": 1}}}}, "tuple_type": null, "type_vars": [], "typeddict_type": null}}, "HiddenInput": {".class": "SymbolTableNode", "cross_ref": "django.forms.widgets.HiddenInput", "kind": "Gdef", "module_public": false}, "ImageField": {".class": "SymbolTableNode", "kind": "Gdef", "node": {".class": "TypeInfo", "_promote": null, "abstract_attributes": [], "bases": ["django.forms.fields.FileField"], "declared_metaclass": null, "defn": {".class": "ClassDef", "fullname": "django.forms.fields.ImageField", "name": "ImageField", "type_vars": []}, "flags": [], "fullname": "django.forms.fields.ImageField", "metaclass_type": null, "metadata": {}, "module_name": "django.forms.fields", "mro": ["django.forms.fields.ImageField", "django.forms.fields.FileField", "django.forms.fields.Field", "builtins.object"], "names": {".class": "SymbolTable", "default_error_messages": {".class": "SymbolTableNode", "kind": "Mdef", "node": {".class": "Var", "flags": ["is_initialized_in_class"], "fullname": "django.forms.fields.ImageField.default_error_messages", "name": "default_error_messages", "type": {".class": "Instance", "args": ["builtins.str", {".class": "AnyType", "missing_import_name": null, "source_any": {".class": "AnyType", "missing_import_name": null, "source_any": null, "type_of_any": 1}, "type_of_any": 7}], "type_ref": "builtins.dict"}}}, "default_validators": {".class": "SymbolTableNode", "kind": "Mdef", "node": {".class": "Var", "flags": ["is_initialized_in_class"], "fullname": "django.forms.fields.ImageField.default_validators", "name": "default_validators", "type": {".class": "Instance", "args": [{".class": "CallableType", "arg_kinds": [0], "arg_names": ["value"], "arg_types": [{".class": "AnyType", "missing_import_name": null, "source_any": null, "type_of_any": 1}], "bound_args": [], "def_extras": {}, "fallback": "builtins.function", "implicit": true, "is_ellipsis_args": false, "name": "validate_image_file_extension", "ret_type": {".class": "AnyType", "missing_import_name": null, "source_any": null, "type_of_any": 1}, "variables": []}], "type_ref": "builtins.list"}}}, "to_python": {".class": "SymbolTableNode", "kind": "Mdef", "node": {".class": "FuncDef", "arg_kinds": [0, 0], "arg_names": ["self", "data"], "flags": [], "fullname": "django.forms.fields.ImageField.to_python", "name": "to_python", "type": null}}, "widget_attrs": {".class": "SymbolTableNode", "kind": "Mdef", "node": {".class": "FuncDef", "arg_kinds": [0, 0], "arg_names": ["self", "widget"], "flags": [], "fullname": "django.forms.fields.ImageField.widget_attrs", "name": "widget_attrs", "type": null}}}, "tuple_type": null, "type_vars": [], "typeddict_type": null}}, "IntegerField": {".class": "SymbolTableNode", "kind": "Gdef", "node": {".class": "TypeInfo", "_promote": null, "abstract_attributes": [], "bases": ["django.forms.fields.Field"], "declared_metaclass": null, "defn": {".class": "ClassDef", "fullname": "django.forms.fields.IntegerField", "name": "IntegerField", "type_vars": []}, "flags": [], "fullname": "django.forms.fields.IntegerField", "metaclass_type": null, "metadata": {}, "module_name": "django.forms.fields", "mro": ["django.forms.fields.IntegerField", "django.forms.fields.Field", "builtins.object"], "names": {".class": "SymbolTable", "__init__": {".class": "SymbolTableNode", "kind": "Mdef", "node": {".class": "FuncDef", "arg_kinds": [0, 5, 5, 4], "arg_names": ["self", "max_value", "min_value", "kwargs"], "flags": [], "fullname": "django.forms.fields.IntegerField.__init__", "name": "__init__", "type": null}}, "default_error_messages": {".class": "SymbolTableNode", "kind": "Mdef", "node": {".class": "Var", "flags": ["is_initialized_in_class"], "fullname": "django.forms.fields.IntegerField.default_error_messages", "name": "default_error_messages", "type": {".class": "Instance", "args": ["builtins.str", {".class": "AnyType", "missing_import_name": null, "source_any": {".class": "AnyType", "missing_import_name": null, "source_any": null, "type_of_any": 1}, "type_of_any": 7}], "type_ref": "builtins.dict"}}}, "max_value": {".class": "SymbolTableNode", "implicit": true, "kind": "Mdef", "node": {".class": "Var", "flags": [], "fullname": "django.forms.fields.IntegerField.max_value", "name": "max_value", "type": {".class": "AnyType", "missing_import_name": null, "source_any": null, "type_of_any": 1}}}, "min_value": {".class": "SymbolTableNode", "implicit": true, "kind": "Mdef", "node": {".class": "Var", "flags": [], "fullname": "django.forms.fields.IntegerField.min_value", "name": "min_value", "type": {".class": "AnyType", "missing_import_name": null, "source_any": null, "type_of_any": 1}}}, "re_decimal": {".class": "SymbolTableNode", "kind": "Mdef", "node": {".class": "Var", "flags": ["is_initialized_in_class"], "fullname": "django.forms.fields.IntegerField.re_decimal", "name": "re_decimal", "type": {".class": "AnyType", "missing_import_name": null, "source_any": null, "type_of_any": 1}}}, "to_python": {".class": "SymbolTableNode", "kind": "Mdef", "node": {".class": "FuncDef", "arg_kinds": [0, 0], "arg_names": ["self", "value"], "flags": [], "fullname": "django.forms.fields.IntegerField.to_python", "name": "to_python", "type": null}}, "widget": {".class": "SymbolTableNode", "kind": "Mdef", "node": {".class": "Var", "flags": ["is_initialized_in_class"], "fullname": "django.forms.fields.IntegerField.widget", "name": "widget", "type": null}}, "widget_attrs": {".class": "SymbolTableNode", "kind": "Mdef", "node": {".class": "FuncDef", "arg_kinds": [0, 0], "arg_names": ["self", "widget"], "flags": [], "fullname": "django.forms.fields.IntegerField.widget_attrs", "name": "widget_attrs", "type": null}}}, "tuple_type": null, "type_vars": [], "typeddict_type": null}}, "InvalidJSONInput": {".class": "SymbolTableNode", "kind": "Gdef", "module_public": false, "node": {".class": "TypeInfo", "_promote": null, "abstract_attributes": [], "bases": ["builtins.str"], "declared_metaclass": null, "defn": {".class": "ClassDef", "fullname": "django.forms.fields.InvalidJSONInput", "name": "InvalidJSONInput", "type_vars": []}, "flags": [], "fullname": "django.forms.fields.InvalidJSONInput", "metaclass_type": "abc.ABCMeta", "metadata": {}, "module_name": "django.forms.fields", "mro": ["django.forms.fields.InvalidJSONInput", "builtins.str", "typing.Sequence", "typing.Collection", "typing.Iterable", "typing.Container", "typing.Reversible", "builtins.object"], "names": {".class": "SymbolTable"}, "tuple_type": null, "type_vars": [], "typeddict_type": null}}, "JSONField": {".class": "SymbolTableNode", "kind": "Gdef", "node": {".class": "TypeInfo", "_promote": null, "abstract_attributes": [], "bases": ["django.forms.fields.CharField"], "declared_metaclass": null, "defn": {".class": "ClassDef", "fullname": "django.forms.fields.JSONField", "name": "JSONField", "type_vars": []}, "flags": [], "fullname": "django.forms.fields.JSONField", "metaclass_type": null, "metadata": {}, "module_name": "django.forms.fields", "mro": ["django.forms.fields.JSONField", "django.forms.fields.CharField", "django.forms.fields.Field", "builtins.object"], "names": {".class": "SymbolTable", "__init__": {".class": "SymbolTableNode", "kind": "Mdef", "node": {".class": "FuncDef", "arg_kinds": [0, 1, 1, 4], "arg_names": ["self", "encoder", "decoder", "kwargs"], "flags": [], "fullname": "django.forms.fields.JSONField.__init__", "name": "__init__", "type": null}}, "bound_data": {".class": "SymbolTableNode", "kind": "Mdef", "node": {".class": "FuncDef", "arg_kinds": [0, 0, 0], "arg_names": ["self", "data", "initial"], "flags": [], "fullname": "django.forms.fields.JSONField.bound_data", "name": "bound_data", "type": null}}, "decoder": {".class": "SymbolTableNode", "implicit": true, "kind": "Mdef", "node": {".class": "Var", "flags": [], "fullname": "django.forms.fields.JSONField.decoder", "name": "decoder", "type": {".class": "AnyType", "missing_import_name": null, "source_any": null, "type_of_any": 1}}}, "default_error_messages": {".class": "SymbolTableNode", "kind": "Mdef", "node": {".class": "Var", "flags": ["is_initialized_in_class"], "fullname": "django.forms.fields.JSONField.default_error_messages", "name": "default_error_messages", "type": {".class": "Instance", "args": ["builtins.str", {".class": "AnyType", "missing_import_name": null, "source_any": {".class": "AnyType", "missing_import_name": null, "source_any": null, "type_of_any": 1}, "type_of_any": 7}], "type_ref": "builtins.dict"}}}, "encoder": {".class": "SymbolTableNode", "implicit": true, "kind": "Mdef", "node": {".class": "Var", "flags": [], "fullname": "django.forms.fields.JSONField.encoder", "name": "encoder", "type": {".class": "AnyType", "missing_import_name": null, "source_any": null, "type_of_any": 1}}}, "has_changed": {".class": "SymbolTableNode", "kind": "Mdef", "node": {".class": "FuncDef", "arg_kinds": [0, 0, 0], "arg_names": ["self", "initial", "data"], "flags": [], "fullname": "django.forms.fields.JSONField.has_changed", "name": "has_changed", "type": null}}, "prepare_value": {".class": "SymbolTableNode", "kind": "Mdef", "node": {".class": "FuncDef", "arg_kinds": [0, 0], "arg_names": ["self", "value"], "flags": [], "fullname": "django.forms.fields.JSONField.prepare_value", "name": "prepare_value", "type": null}}, "to_python": {".class": "SymbolTableNode", "kind": "Mdef", "node": {".class": "FuncDef", "arg_kinds": [0, 0], "arg_names": ["self", "value"], "flags": [], "fullname": "django.forms.fields.JSONField.to_python", "name": "to_python", "type": null}}, "widget": {".class": "SymbolTableNode", "kind": "Mdef", "node": {".class": "Var", "flags": ["is_initialized_in_class"], "fullname": "django.forms.fields.JSONField.widget", "name": "widget", "type": null}}}, "tuple_type": null, "type_vars": [], "typeddict_type": null}}, "JSONString": {".class": "SymbolTableNode", "kind": "Gdef", "module_public": false, "node": {".class": "TypeInfo", "_promote": null, "abstract_attributes": [], "bases": ["builtins.str"], "declared_metaclass": null, "defn": {".class": "ClassDef", "fullname": "django.forms.fields.JSONString", "name": "JSONString", "type_vars": []}, "flags": [], "fullname": "django.forms.fields.JSONString", "metaclass_type": "abc.ABCMeta", "metadata": {}, "module_name": "django.forms.fields", "mro": ["django.forms.fields.JSONString", "builtins.str", "typing.Sequence", "typing.Collection", "typing.Iterable", "typing.Container", "typing.Reversible", "builtins.object"], "names": {".class": "SymbolTable"}, "tuple_type": null, "type_vars": [], "typeddict_type": null}}, "MultiValueField": {".class": "SymbolTableNode", "kind": "Gdef", "node": {".class": "TypeInfo", "_promote": null, "abstract_attributes": [], "bases": ["django.forms.fields.Field"], "declared_metaclass": null, "defn": {".class": "ClassDef", "fullname": "django.forms.fields.MultiValueField", "name": "MultiValueField", "type_vars": []}, "flags": [], "fullname": "django.forms.fields.MultiValueField", "metaclass_type": null, "metadata": {}, "module_name": "django.forms.fields", "mro": ["django.forms.fields.MultiValueField", "django.forms.fields.Field", "builtins.object"], "names": {".class": "SymbolTable", "__deepcopy__": {".class": "SymbolTableNode", "kind": "Mdef", "node": {".class": "FuncDef", "arg_kinds": [0, 0], "arg_names": ["self", "memo"], "flags": [], "fullname": "django.forms.fields.MultiValueField.__deepcopy__", "name": "__deepcopy__", "type": null}}, "__init__": {".class": "SymbolTableNode", "kind": "Mdef", "node": {".class": "FuncDef", "arg_kinds": [0, 0, 5, 4], "arg_names": ["self", "fields", "require_all_fields", "kwargs"], "flags": [], "fullname": "django.forms.fields.MultiValueField.__init__", "name": "__init__", "type": null}}, "clean": {".class": "SymbolTableNode", "kind": "Mdef", "node": {".class": "FuncDef", "arg_kinds": [0, 0], "arg_names": ["self", "value"], "flags": [], "fullname": "django.forms.fields.MultiValueField.clean", "name": "clean", "type": null}}, "compress": {".class": "SymbolTableNode", "kind": "Mdef", "node": {".class": "FuncDef", "arg_kinds": [0, 0], "arg_names": ["self", "data_list"], "flags": [], "fullname": "django.forms.fields.MultiValueField.compress", "name": "compress", "type": null}}, "default_error_messages": {".class": "SymbolTableNode", "kind": "Mdef", "node": {".class": "Var", "flags": ["is_initialized_in_class"], "fullname": "django.forms.fields.MultiValueField.default_error_messages", "name": "default_error_messages", "type": {".class": "Instance", "args": ["builtins.str", {".class": "AnyType", "missing_import_name": null, "source_any": {".class": "AnyType", "missing_import_name": null, "source_any": null, "type_of_any": 1}, "type_of_any": 7}], "type_ref": "builtins.dict"}}}, "fields": {".class": "SymbolTableNode", "implicit": true, "kind": "Mdef", "node": {".class": "Var", "flags": [], "fullname": "django.forms.fields.MultiValueField.fields", "name": "fields", "type": {".class": "AnyType", "missing_import_name": null, "source_any": null, "type_of_any": 1}}}, "has_changed": {".class": "SymbolTableNode", "kind": "Mdef", "node": {".class": "FuncDef", "arg_kinds": [0, 0, 0], "arg_names": ["self", "initial", "data"], "flags": [], "fullname": "django.forms.fields.MultiValueField.has_changed", "name": "has_changed", "type": null}}, "require_all_fields": {".class": "SymbolTableNode", "implicit": true, "kind": "Mdef", "node": {".class": "Var", "flags": [], "fullname": "django.forms.fields.MultiValueField.require_all_fields", "name": "require_all_fields", "type": {".class": "AnyType", "missing_import_name": null, "source_any": null, "type_of_any": 1}}}, "validate": {".class": "SymbolTableNode", "kind": "Mdef", "node": {".class": "FuncDef", "arg_kinds": [0, 0], "arg_names": ["self", "value"], "flags": [], "fullname": "django.forms.fields.MultiValueField.validate", "name": "validate", "type": null}}}, "tuple_type": null, "type_vars": [], "typeddict_type": null}}, "MultipleChoiceField": {".class": "SymbolTableNode", "kind": "Gdef", "node": {".class": "TypeInfo", "_promote": null, "abstract_attributes": [], "bases": ["django.forms.fields.ChoiceField"], "declared_metaclass": null, "defn": {".class": "ClassDef", "fullname": "django.forms.fields.MultipleChoiceField", "name": "MultipleChoiceField", "type_vars": []}, "flags": [], "fullname": "django.forms.fields.MultipleChoiceField", "metaclass_type": null, "metadata": {}, "module_name": "django.forms.fields", "mro": ["django.forms.fields.MultipleChoiceField", "django.forms.fields.ChoiceField", "django.forms.fields.Field", "builtins.object"], "names": {".class": "SymbolTable", "default_error_messages": {".class": "SymbolTableNode", "kind": "Mdef", "node": {".class": "Var", "flags": ["is_initialized_in_class"], "fullname": "django.forms.fields.MultipleChoiceField.default_error_messages", "name": "default_error_messages", "type": {".class": "Instance", "args": ["builtins.str", {".class": "AnyType", "missing_import_name": null, "source_any": {".class": "AnyType", "missing_import_name": null, "source_any": null, "type_of_any": 1}, "type_of_any": 7}], "type_ref": "builtins.dict"}}}, "has_changed": {".class": "SymbolTableNode", "kind": "Mdef", "node": {".class": "FuncDef", "arg_kinds": [0, 0, 0], "arg_names": ["self", "initial", "data"], "flags": [], "fullname": "django.forms.fields.MultipleChoiceField.has_changed", "name": "has_changed", "type": null}}, "hidden_widget": {".class": "SymbolTableNode", "kind": "Mdef", "node": {".class": "Var", "flags": ["is_initialized_in_class"], "fullname": "django.forms.fields.MultipleChoiceField.hidden_widget", "name": "hidden_widget", "type": {".class": "CallableType", "arg_kinds": [1], "arg_names": ["attrs"], "arg_types": [{".class": "AnyType", "missing_import_name": null, "source_any": null, "type_of_any": 1}], "bound_args": ["django.forms.widgets.MultipleHiddenInput"], "def_extras": {}, "fallback": "django.forms.widgets.MediaDefiningClass", "implicit": true, "is_ellipsis_args": false, "name": null, "ret_type": "django.forms.widgets.MultipleHiddenInput", "variables": []}}}, "to_python": {".class": "SymbolTableNode", "kind": "Mdef", "node": {".class": "FuncDef", "arg_kinds": [0, 0], "arg_names": ["self", "value"], "flags": [], "fullname": "django.forms.fields.MultipleChoiceField.to_python", "name": "to_python", "type": null}}, "validate": {".class": "SymbolTableNode", "kind": "Mdef", "node": {".class": "FuncDef", "arg_kinds": [0, 0], "arg_names": ["self", "value"], "flags": [], "fullname": "django.forms.fields.MultipleChoiceField.validate", "name": "validate", "type": null}}, "widget": {".class": "SymbolTableNode", "kind": "Mdef", "node": {".class": "Var", "flags": ["is_initialized_in_class"], "fullname": "django.forms.fields.MultipleChoiceField.widget", "name": "widget", "type": null}}}, "tuple_type": null, "type_vars": [], "typeddict_type": null}}, "MultipleHiddenInput": {".class": "SymbolTableNode", "cross_ref": "django.forms.widgets.MultipleHiddenInput", "kind": "Gdef", "module_public": false}, "NullBooleanField": {".class": "SymbolTableNode", "kind": "Gdef", "node": {".class": "TypeInfo", "_promote": null, "abstract_attributes": [], "bases": ["django.forms.fields.BooleanField"], "declared_metaclass": null, "defn": {".class": "ClassDef", "fullname": "django.forms.fields.NullBooleanField", "name": "NullBooleanField", "type_vars": []}, "flags": [], "fullname": "django.forms.fields.NullBooleanField", "metaclass_type": null, "metadata": {}, "module_name": "django.forms.fields", "mro": ["django.forms.fields.NullBooleanField", "django.forms.fields.BooleanField", "django.forms.fields.Field", "builtins.object"], "names": {".class": "SymbolTable", "to_python": {".class": "SymbolTableNode", "kind": "Mdef", "node": {".class": "FuncDef", "arg_kinds": [0, 0], "arg_names": ["self", "value"], "flags": [], "fullname": "django.forms.fields.NullBooleanField.to_python", "name": "to_python", "type": null}}, "validate": {".class": "SymbolTableNode", "kind": "Mdef", "node": {".class": "FuncDef", "arg_kinds": [0, 0], "arg_names": ["self", "value"], "flags": [], "fullname": "django.forms.fields.NullBooleanField.validate", "name": "validate", "type": null}}, "widget": {".class": "SymbolTableNode", "kind": "Mdef", "node": {".class": "Var", "flags": ["is_initialized_in_class"], "fullname": "django.forms.fields.NullBooleanField.widget", "name": "widget", "type": null}}}, "tuple_type": null, "type_vars": [], "typeddict_type": null}}, "NullBooleanSelect": {".class": "SymbolTableNode", "cross_ref": "django.forms.widgets.NullBooleanSelect", "kind": "Gdef", "module_public": false}, "NumberInput": {".class": "SymbolTableNode", "cross_ref": "django.forms.widgets.NumberInput", "kind": "Gdef", "module_public": false}, "RegexField": {".class": "SymbolTableNode", "kind": "Gdef", "node": {".class": "TypeInfo", "_promote": null, "abstract_attributes": [], "bases": ["django.forms.fields.CharField"], "declared_metaclass": null, "defn": {".class": "ClassDef", "fullname": "django.forms.fields.RegexField", "name": "RegexField", "type_vars": []}, "flags": [], "fullname": "django.forms.fields.RegexField", "metaclass_type": null, "metadata": {}, "module_name": "django.forms.fields", "mro": ["django.forms.fields.RegexField", "django.forms.fields.CharField", "django.forms.fields.Field", "builtins.object"], "names": {".class": "SymbolTable", "__init__": {".class": "SymbolTableNode", "kind": "Mdef", "node": {".class": "FuncDef", "arg_kinds": [0, 0, 4], "arg_names": ["self", "regex", "kwargs"], "flags": [], "fullname": "django.forms.fields.RegexField.__init__", "name": "__init__", "type": null}}, "_get_regex": {".class": "SymbolTableNode", "kind": "Mdef", "node": {".class": "FuncDef", "arg_kinds": [0], "arg_names": ["self"], "flags": [], "fullname": "django.forms.fields.RegexField._get_regex", "name": "_get_regex", "type": null}}, "_regex": {".class": "SymbolTableNode", "implicit": true, "kind": "Mdef", "node": {".class": "Var", "flags": [], "fullname": "django.forms.fields.RegexField._regex", "name": "_regex", "type": {".class": "AnyType", "missing_import_name": null, "source_any": null, "type_of_any": 1}}}, "_regex_validator": {".class": "SymbolTableNode", "implicit": true, "kind": "Mdef", "node": {".class": "Var", "flags": [], "fullname": "django.forms.fields.RegexField._regex_validator", "name": "_regex_validator", "type": {".class": "AnyType", "missing_import_name": null, "source_any": null, "type_of_any": 1}}}, "_set_regex": {".class": "SymbolTableNode", "kind": "Mdef", "node": {".class": "FuncDef", "arg_kinds": [0, 0], "arg_names": ["self", "regex"], "flags": [], "fullname": "django.forms.fields.RegexField._set_regex", "name": "_set_regex", "type": null}}, "regex": {".class": "SymbolTableNode", "kind": "Mdef", "node": {".class": "Var", "flags": ["is_initialized_in_class"], "fullname": "django.forms.fields.RegexField.regex", "name": "regex", "type": "builtins.property"}}}, "tuple_type": null, "type_vars": [], "typeddict_type": null}}, "Select": {".class": "SymbolTableNode", "cross_ref": "django.forms.widgets.Select", "kind": "Gdef", "module_public": false}, "SelectMultiple": {".class": "SymbolTableNode", "cross_ref": "django.forms.widgets.SelectMultiple", "kind": "Gdef", "module_public": false}, "SlugField": {".class": "SymbolTableNode", "kind": "Gdef", "node": {".class": "TypeInfo", "_promote": null, "abstract_attributes": [], "bases": ["django.forms.fields.CharField"], "declared_metaclass": null, "defn": {".class": "ClassDef", "fullname": "django.forms.fields.SlugField", "name": "SlugField", "type_vars": []}, "flags": [], "fullname": "django.forms.fields.SlugField", "metaclass_type": null, "metadata": {}, "module_name": "django.forms.fields", "mro": ["django.forms.fields.SlugField", "django.forms.fields.CharField", "django.forms.fields.Field", "builtins.object"], "names": {".class": "SymbolTable", "__init__": {".class": "SymbolTableNode", "kind": "Mdef", "node": {".class": "FuncDef", "arg_kinds": [0, 5, 4], "arg_names": ["self", "allow_unicode", "kwargs"], "flags": [], "fullname": "django.forms.fields.SlugField.__init__", "name": "__init__", "type": null}}, "allow_unicode": {".class": "SymbolTableNode", "implicit": true, "kind": "Mdef", "node": {".class": "Var", "flags": [], "fullname": "django.forms.fields.SlugField.allow_unicode", "name": "allow_unicode", "type": {".class": "AnyType", "missing_import_name": null, "source_any": null, "type_of_any": 1}}}, "default_validators": {".class": "SymbolTableNode", "kind": "Mdef", "node": {".class": "Var", "flags": ["is_initialized_in_class"], "fullname": "django.forms.fields.SlugField.default_validators", "name": "default_validators", "type": {".class": "Instance", "args": ["django.core.validators.RegexValidator"], "type_ref": "builtins.list"}}}}, "tuple_type": null, "type_vars": [], "typeddict_type": null}}, "SplitDateTimeField": {".class": "SymbolTableNode", "kind": "Gdef", "node": {".class": "TypeInfo", "_promote": null, "abstract_attributes": [], "bases": ["django.forms.fields.MultiValueField"], "declared_metaclass": null, "defn": {".class": "ClassDef", "fullname": "django.forms.fields.SplitDateTimeField", "name": "SplitDateTimeField", "type_vars": []}, "flags": [], "fullname": "django.forms.fields.SplitDateTimeField", "metaclass_type": null, "metadata": {}, "module_name": "django.forms.fields", "mro": ["django.forms.fields.SplitDateTimeField", "django.forms.fields.MultiValueField", "django.forms.fields.Field", "builtins.object"], "names": {".class": "SymbolTable", "__init__": {".class": "SymbolTableNode", "kind": "Mdef", "node": {".class": "FuncDef", "arg_kinds": [0, 5, 5, 4], "arg_names": ["self", "input_date_formats", "input_time_formats", "kwargs"], "flags": [], "fullname": "django.forms.fields.SplitDateTimeField.__init__", "name": "__init__", "type": null}}, "compress": {".class": "SymbolTableNode", "kind": "Mdef", "node": {".class": "FuncDef", "arg_kinds": [0, 0], "arg_names": ["self", "data_list"], "flags": [], "fullname": "django.forms.fields.SplitDateTimeField.compress", "name": "compress", "type": null}}, "default_error_messages": {".class": "SymbolTableNode", "kind": "Mdef", "node": {".class": "Var", "flags": ["is_initialized_in_class"], "fullname": "django.forms.fields.SplitDateTimeField.default_error_messages", "name": "default_error_messages", "type": {".class": "Instance", "args": ["builtins.str", {".class": "AnyType", "missing_import_name": null, "source_any": {".class": "AnyType", "missing_import_name": null, "source_any": null, "type_of_any": 1}, "type_of_any": 7}], "type_ref": "builtins.dict"}}}, "hidden_widget": {".class": "SymbolTableNode", "kind": "Mdef", "node": {".class": "Var", "flags": ["is_initialized_in_class"], "fullname": "django.forms.fields.SplitDateTimeField.hidden_widget", "name": "hidden_widget", "type": null}}, "widget": {".class": "SymbolTableNode", "kind": "Mdef", "node": {".class": "Var", "flags": ["is_initialized_in_class"], "fullname": "django.forms.fields.SplitDateTimeField.widget", "name": "widget", "type": null}}}, "tuple_type": null, "type_vars": [], "typeddict_type": null}}, "SplitDateTimeWidget": {".class": "SymbolTableNode", "cross_ref": "django.forms.widgets.SplitDateTimeWidget", "kind": "Gdef", "module_public": false}, "SplitHiddenDateTimeWidget": {".class": "SymbolTableNode", "cross_ref": "django.forms.widgets.SplitHiddenDateTimeWidget", "kind": "Gdef", "module_public": false}, "TextInput": {".class": "SymbolTableNode", "cross_ref": "django.forms.widgets.TextInput", "kind": "Gdef", "module_public": false}, "Textarea": {".class": "SymbolTableNode", "cross_ref": "django.forms.widgets.Textarea", "kind": "Gdef", "module_public": false}, "TimeField": {".class": "SymbolTableNode", "kind": "Gdef", "node": {".class": "TypeInfo", "_promote": null, "abstract_attributes": [], "bases": ["django.forms.fields.BaseTemporalField"], "declared_metaclass": null, "defn": {".class": "ClassDef", "fullname": "django.forms.fields.TimeField", "name": "TimeField", "type_vars": []}, "flags": [], "fullname": "django.forms.fields.TimeField", "metaclass_type": null, "metadata": {}, "module_name": "django.forms.fields", "mro": ["django.forms.fields.TimeField", "django.forms.fields.BaseTemporalField", "django.forms.fields.Field", "builtins.object"], "names": {".class": "SymbolTable", "default_error_messages": {".class": "SymbolTableNode", "kind": "Mdef", "node": {".class": "Var", "flags": ["is_initialized_in_class"], "fullname": "django.forms.fields.TimeField.default_error_messages", "name": "default_error_messages", "type": {".class": "Instance", "args": ["builtins.str", {".class": "AnyType", "missing_import_name": null, "source_any": {".class": "AnyType", "missing_import_name": null, "source_any": null, "type_of_any": 1}, "type_of_any": 7}], "type_ref": "builtins.dict"}}}, "input_formats": {".class": "SymbolTableNode", "kind": "Mdef", "node": {".class": "Var", "flags": ["is_initialized_in_class"], "fullname": "django.forms.fields.TimeField.input_formats", "name": "input_formats", "type": {".class": "AnyType", "missing_import_name": null, "source_any": {".class": "AnyType", "missing_import_name": null, "source_any": null, "type_of_any": 1}, "type_of_any": 7}}}, "strptime": {".class": "SymbolTableNode", "kind": "Mdef", "node": {".class": "FuncDef", "arg_kinds": [0, 0, 0], "arg_names": ["self", "value", "format"], "flags": [], "fullname": "django.forms.fields.TimeField.strptime", "name": "strptime", "type": null}}, "to_python": {".class": "SymbolTableNode", "kind": "Mdef", "node": {".class": "FuncDef", "arg_kinds": [0, 0], "arg_names": ["self", "value"], "flags": [], "fullname": "django.forms.fields.TimeField.to_python", "name": "to_python", "type": null}}, "widget": {".class": "SymbolTableNode", "kind": "Mdef", "node": {".class": "Var", "flags": ["is_initialized_in_class"], "fullname": "django.forms.fields.TimeField.widget", "name": "widget", "type": {".class": "CallableType", "arg_kinds": [1, 1], "arg_names": ["attrs", "format"], "arg_types": [{".class": "AnyType", "missing_import_name": null, "source_any": null, "type_of_any": 1}, {".class": "AnyType", "missing_import_name": null, "source_any": null, "type_of_any": 1}], "bound_args": ["django.forms.widgets.TimeInput"], "def_extras": {}, "fallback": "django.forms.widgets.MediaDefiningClass", "implicit": true, "is_ellipsis_args": false, "name": null, "ret_type": "django.forms.widgets.TimeInput", "variables": []}}}}, "tuple_type": null, "type_vars": [], "typeddict_type": null}}, "TimeInput": {".class": "SymbolTableNode", "cross_ref": "django.forms.widgets.TimeInput", "kind": "Gdef", "module_public": false}, "TypedChoiceField": {".class": "SymbolTableNode", "kind": "Gdef", "node": {".class": "TypeInfo", "_promote": null, "abstract_attributes": [], "bases": ["django.forms.fields.ChoiceField"], "declared_metaclass": null, "defn": {".class": "ClassDef", "fullname": "django.forms.fields.TypedChoiceField", "name": "TypedChoiceField", "type_vars": []}, "flags": [], "fullname": "django.forms.fields.TypedChoiceField", "metaclass_type": null, "metadata": {}, "module_name": "django.forms.fields", "mro": ["django.forms.fields.TypedChoiceField", "django.forms.fields.ChoiceField", "django.forms.fields.Field", "builtins.object"], "names": {".class": "SymbolTable", "__init__": {".class": "SymbolTableNode", "kind": "Mdef", "node": {".class": "FuncDef", "arg_kinds": [0, 5, 5, 4], "arg_names": ["self", "coerce", "empty_value", "kwargs"], "flags": [], "fullname": "django.forms.fields.TypedChoiceField.__init__", "name": "__init__", "type": null}}, "_coerce": {".class": "SymbolTableNode", "kind": "Mdef", "node": {".class": "FuncDef", "arg_kinds": [0, 0], "arg_names": ["self", "value"], "flags": [], "fullname": "django.forms.fields.TypedChoiceField._coerce", "name": "_coerce", "type": null}}, "clean": {".class": "SymbolTableNode", "kind": "Mdef", "node": {".class": "FuncDef", "arg_kinds": [0, 0], "arg_names": ["self", "value"], "flags": [], "fullname": "django.forms.fields.TypedChoiceField.clean", "name": "clean", "type": null}}, "coerce": {".class": "SymbolTableNode", "implicit": true, "kind": "Mdef", "node": {".class": "Var", "flags": [], "fullname": "django.forms.fields.TypedChoiceField.coerce", "name": "coerce", "type": {".class": "AnyType", "missing_import_name": null, "source_any": null, "type_of_any": 1}}}, "empty_value": {".class": "SymbolTableNode", "implicit": true, "kind": "Mdef", "node": {".class": "Var", "flags": [], "fullname": "django.forms.fields.TypedChoiceField.empty_value", "name": "empty_value", "type": {".class": "AnyType", "missing_import_name": null, "source_any": null, "type_of_any": 1}}}}, "tuple_type": null, "type_vars": [], "typeddict_type": null}}, "TypedMultipleChoiceField": {".class": "SymbolTableNode", "kind": "Gdef", "node": {".class": "TypeInfo", "_promote": null, "abstract_attributes": [], "bases": ["django.forms.fields.MultipleChoiceField"], "declared_metaclass": null, "defn": {".class": "ClassDef", "fullname": "django.forms.fields.TypedMultipleChoiceField", "name": "TypedMultipleChoiceField", "type_vars": []}, "flags": [], "fullname": "django.forms.fields.TypedMultipleChoiceField", "metaclass_type": null, "metadata": {}, "module_name": "django.forms.fields", "mro": ["django.forms.fields.TypedMultipleChoiceField", "django.forms.fields.MultipleChoiceField", "django.forms.fields.ChoiceField", "django.forms.fields.Field", "builtins.object"], "names": {".class": "SymbolTable", "__init__": {".class": "SymbolTableNode", "kind": "Mdef", "node": {".class": "FuncDef", "arg_kinds": [0, 5, 4], "arg_names": ["self", "coerce", "kwargs"], "flags": [], "fullname": "django.forms.fields.TypedMultipleChoiceField.__init__", "name": "__init__", "type": null}}, "_coerce": {".class": "SymbolTableNode", "kind": "Mdef", "node": {".class": "FuncDef", "arg_kinds": [0, 0], "arg_names": ["self", "value"], "flags": [], "fullname": "django.forms.fields.TypedMultipleChoiceField._coerce", "name": "_coerce", "type": null}}, "clean": {".class": "SymbolTableNode", "kind": "Mdef", "node": {".class": "FuncDef", "arg_kinds": [0, 0], "arg_names": ["self", "value"], "flags": [], "fullname": "django.forms.fields.TypedMultipleChoiceField.clean", "name": "clean", "type": null}}, "coerce": {".class": "SymbolTableNode", "implicit": true, "kind": "Mdef", "node": {".class": "Var", "flags": [], "fullname": "django.forms.fields.TypedMultipleChoiceField.coerce", "name": "coerce", "type": {".class": "AnyType", "missing_import_name": null, "source_any": null, "type_of_any": 1}}}, "empty_value": {".class": "SymbolTableNode", "implicit": true, "kind": "Mdef", "node": {".class": "Var", "flags": [], "fullname": "django.forms.fields.TypedMultipleChoiceField.empty_value", "name": "empty_value", "type": {".class": "AnyType", "missing_import_name": null, "source_any": null, "type_of_any": 1}}}, "validate": {".class": "SymbolTableNode", "kind": "Mdef", "node": {".class": "FuncDef", "arg_kinds": [0, 0], "arg_names": ["self", "value"], "flags": [], "fullname": "django.forms.fields.TypedMultipleChoiceField.validate", "name": "validate", "type": null}}}, "tuple_type": null, "type_vars": [], "typeddict_type": null}}, "URLField": {".class": "SymbolTableNode", "kind": "Gdef", "node": {".class": "TypeInfo", "_promote": null, "abstract_attributes": [], "bases": ["django.forms.fields.CharField"], "declared_metaclass": null, "defn": {".class": "ClassDef", "fullname": "django.forms.fields.URLField", "name": "URLField", "type_vars": []}, "flags": [], "fullname": "django.forms.fields.URLField", "metaclass_type": null, "metadata": {}, "module_name": "django.forms.fields", "mro": ["django.forms.fields.URLField", "django.forms.fields.CharField", "django.forms.fields.Field", "builtins.object"], "names": {".class": "SymbolTable", "__init__": {".class": "SymbolTableNode", "kind": "Mdef", "node": {".class": "FuncDef", "arg_kinds": [0, 4], "arg_names": ["self", "kwargs"], "flags": [], "fullname": "django.forms.fields.URLField.__init__", "name": "__init__", "type": null}}, "default_error_messages": {".class": "SymbolTableNode", "kind": "Mdef", "node": {".class": "Var", "flags": ["is_initialized_in_class"], "fullname": "django.forms.fields.URLField.default_error_messages", "name": "default_error_messages", "type": {".class": "Instance", "args": ["builtins.str", {".class": "AnyType", "missing_import_name": null, "source_any": {".class": "AnyType", "missing_import_name": null, "source_any": null, "type_of_any": 1}, "type_of_any": 7}], "type_ref": "builtins.dict"}}}, "default_validators": {".class": "SymbolTableNode", "kind": "Mdef", "node": {".class": "Var", "flags": ["is_initialized_in_class"], "fullname": "django.forms.fields.URLField.default_validators", "name": "default_validators", "type": {".class": "Instance", "args": ["django.core.validators.URLValidator"], "type_ref": "builtins.list"}}}, "to_python": {".class": "SymbolTableNode", "kind": "Mdef", "node": {".class": "FuncDef", "arg_kinds": [0, 0], "arg_names": ["self", "value"], "flags": [], "fullname": "django.forms.fields.URLField.to_python", "name": "to_python", "type": null}}, "widget": {".class": "SymbolTableNode", "kind": "Mdef", "node": {".class": "Var", "flags": ["is_initialized_in_class"], "fullname": "django.forms.fields.URLField.widget", "name": "widget", "type": null}}}, "tuple_type": null, "type_vars": [], "typeddict_type": null}}, "URLInput": {".class": "SymbolTableNode", "cross_ref": "django.forms.widgets.URLInput", "kind": "Gdef", "module_public": false}, "UUIDField": {".class": "SymbolTableNode", "kind": "Gdef", "node": {".class": "TypeInfo", "_promote": null, "abstract_attributes": [], "bases": ["django.forms.fields.CharField"], "declared_metaclass": null, "defn": {".class": "ClassDef", "fullname": "django.forms.fields.UUIDField", "name": "UUIDField", "type_vars": []}, "flags": [], "fullname": "django.forms.fields.UUIDField", "metaclass_type": null, "metadata": {}, "module_name": "django.forms.fields", "mro": ["django.forms.fields.UUIDField", "django.forms.fields.CharField", "django.forms.fields.Field", "builtins.object"], "names": {".class": "SymbolTable", "default_error_messages": {".class": "SymbolTableNode", "kind": "Mdef", "node": {".class": "Var", "flags": ["is_initialized_in_class"], "fullname": "django.forms.fields.UUIDField.default_error_messages", "name": "default_error_messages", "type": {".class": "Instance", "args": ["builtins.str", {".class": "AnyType", "missing_import_name": null, "source_any": {".class": "AnyType", "missing_import_name": null, "source_any": null, "type_of_any": 1}, "type_of_any": 7}], "type_ref": "builtins.dict"}}}, "prepare_value": {".class": "SymbolTableNode", "kind": "Mdef", "node": {".class": "FuncDef", "arg_kinds": [0, 0], "arg_names": ["self", "value"], "flags": [], "fullname": "django.forms.fields.UUIDField.prepare_value", "name": "prepare_value", "type": null}}, "to_python": {".class": "SymbolTableNode", "kind": "Mdef", "node": {".class": "FuncDef", "arg_kinds": [0, 0], "arg_names": ["self", "value"], "flags": [], "fullname": "django.forms.fields.UUIDField.to_python", "name": "to_python", "type": null}}}, "tuple_type": null, "type_vars": [], "typeddict_type": null}}, "ValidationError": {".class": "SymbolTableNode", "cross_ref": "django.core.exceptions.ValidationError", "kind": "Gdef", "module_public": false}, "_": {".class": "SymbolTableNode", "cross_ref": "django.utils.translation.gettext_lazy", "kind": "Gdef", "module_public": false}, "__all__": {".class": "SymbolTableNode", "kind": "Gdef", "module_public": false, "node": {".class": "Var", "flags": [], "fullname": "django.forms.fields.__all__", "name": "__all__", "type": {".class": "TupleType", "implicit": false, "items": ["builtins.str", "builtins.str", "builtins.str", "builtins.str", "builtins.str", "builtins.str", "builtins.str", "builtins.str", "builtins.str", "builtins.str", "builtins.str", "builtins.str", "builtins.str", "builtins.str", "builtins.str", "builtins.str", "builtins.str", "builtins.str", "builtins.str", "builtins.str", "builtins.str", "builtins.str", "builtins.str", "builtins.str", "builtins.str", "builtins.str", "builtins.str", "builtins.str"], "partial_fallback": {".class": "Instance", "args": [{".class": "AnyType", "missing_import_name": null, "source_any": null, "type_of_any": 6}], "type_ref": "builtins.tuple"}}}}, "__doc__": {".class": "SymbolTableNode", "kind": "Gdef", "module_public": false, "node": {".class": "Var", "flags": ["is_ready"], "fullname": "django.forms.fields.__doc__", "name": "__doc__", "type": "builtins.str"}}, "__file__": {".class": "SymbolTableNode", "kind": "Gdef", "module_public": false, "node": {".class": "Var", "flags": ["is_ready"], "fullname": "django.forms.fields.__file__", "name": "__file__", "type": "builtins.str"}}, "__name__": {".class": "SymbolTableNode", "kind": "Gdef", "module_public": false, "node": {".class": "Var", "flags": ["is_ready"], "fullname": "django.forms.fields.__name__", "name": "__name__", "type": "builtins.str"}}, "__package__": {".class": "SymbolTableNode", "kind": "Gdef", "module_public": false, "node": {".class": "Var", "flags": ["is_ready"], "fullname": "django.forms.fields.__package__", "name": "__package__", "type": "builtins.str"}}, "_lazy_re_compile": {".class": "SymbolTableNode", "cross_ref": "django.utils.regex_helper._lazy_re_compile", "kind": "Gdef", "module_public": false}, "clean_ipv6_address": {".class": "SymbolTableNode", "cross_ref": "django.utils.ipv6.clean_ipv6_address", "kind": "Gdef", "module_public": false}, "copy": {".class": "SymbolTableNode", "cross_ref": "copy", "kind": "Gdef", "module_public": false}, "datetime": {".class": "SymbolTableNode", "cross_ref": "datetime", "kind": "Gdef", "module_public": false}, "duration_string": {".class": "SymbolTableNode", "cross_ref": "django.utils.duration.duration_string", "kind": "Gdef", "module_public": false}, "formats": {".class": "SymbolTableNode", "cross_ref": "django.utils.formats", "kind": "Gdef", "module_public": false}, "from_current_timezone": {".class": "SymbolTableNode", "cross_ref": "django.forms.utils.from_current_timezone", "kind": "Gdef", "module_public": false}, "json": {".class": "SymbolTableNode", "cross_ref": "json", "kind": "Gdef", "module_public": false}, "math": {".class": "SymbolTableNode", "cross_ref": "math", "kind": "Gdef", "module_public": false}, "ngettext_lazy": {".class": "SymbolTableNode", "cross_ref": "django.utils.translation.ngettext_lazy", "kind": "Gdef", "module_public": false}, "operator": {".class": "SymbolTableNode", "cross_ref": "operator", "kind": "Gdef", "module_public": false}, "os": {".class": "SymbolTableNode", "cross_ref": "os", "kind": "Gdef", "module_public": false}, "parse_datetime": {".class": "SymbolTableNode", "cross_ref": "django.utils.dateparse.parse_datetime", "kind": "Gdef", "module_public": false}, "parse_duration": {".class": "SymbolTableNode", "cross_ref": "django.utils.dateparse.parse_duration", "kind": "Gdef", "module_public": false}, "re": {".class": "SymbolTableNode", "cross_ref": "re", "kind": "Gdef", "module_public": false}, "to_current_timezone": {".class": "SymbolTableNode", "cross_ref": "django.forms.utils.to_current_timezone", "kind": "Gdef", "module_public": false}, "urlsplit": {".class": "SymbolTableNode", "cross_ref": "urllib.parse.urlsplit", "kind": "Gdef", "module_public": false}, "urlunsplit": {".class": "SymbolTableNode", "cross_ref": "urllib.parse.urlunsplit", "kind": "Gdef", "module_public": false}, "uuid": {".class": "SymbolTableNode", "cross_ref": "uuid", "kind": "Gdef", "module_public": false}, "validators": {".class": "SymbolTableNode", "cross_ref": "django.core.validators", "kind": "Gdef", "module_public": false}}, "path": "/home/ibrahim/opensrc/django/django/forms/fields.py"}