{".class": "MypyFile", "_fullname": "django.forms.forms", "is_partial_stub_package": false, "is_stub": false, "names": {".class": "SymbolTable", "BaseForm": {".class": "SymbolTableNode", "kind": "Gdef", "node": {".class": "TypeInfo", "_promote": null, "abstract_attributes": [], "bases": ["builtins.object"], "declared_metaclass": null, "defn": {".class": "ClassDef", "fullname": "django.forms.forms.BaseForm", "name": "BaseForm", "type_vars": []}, "flags": [], "fullname": "django.forms.forms.BaseForm", "metaclass_type": null, "metadata": {}, "module_name": "django.forms.forms", "mro": ["django.forms.forms.BaseForm", "builtins.object"], "names": {".class": "SymbolTable", "__getitem__": {".class": "SymbolTableNode", "kind": "Mdef", "node": {".class": "FuncDef", "arg_kinds": [0, 0], "arg_names": ["self", "name"], "flags": [], "fullname": "django.forms.forms.BaseForm.__getitem__", "name": "__getitem__", "type": null}}, "__init__": {".class": "SymbolTableNode", "kind": "Mdef", "node": {".class": "FuncDef", "arg_kinds": [0, 1, 1, 1, 1, 1, 1, 1, 1, 1, 1, 1], "arg_names": ["self", "data", "files", "auto_id", "prefix", "initial", "error_class", "label_suffix", "empty_permitted", "field_order", "use_required_attribute", "renderer"], "flags": [], "fullname": "django.forms.forms.BaseForm.__init__", "name": "__init__", "type": null}}, "__iter__": {".class": "SymbolTableNode", "kind": "Mdef", "node": {".class": "FuncDef", "arg_kinds": [0], "arg_names": ["self"], "flags": ["is_generator"], "fullname": "django.forms.forms.BaseForm.__iter__", "name": "__iter__", "type": null}}, "__repr__": {".class": "SymbolTableNode", "kind": "Mdef", "node": {".class": "FuncDef", "arg_kinds": [0], "arg_names": ["self"], "flags": [], "fullname": "django.forms.forms.BaseForm.__repr__", "name": "__repr__", "type": null}}, "__str__": {".class": "SymbolTableNode", "kind": "Mdef", "node": {".class": "FuncDef", "arg_kinds": [0], "arg_names": ["self"], "flags": [], "fullname": "django.forms.forms.BaseForm.__str__", "name": "__str__", "type": null}}, "_bound_fields_cache": {".class": "SymbolTableNode", "implicit": true, "kind": "Mdef", "node": {".class": "Var", "flags": [], "fullname": "django.forms.forms.BaseForm._bound_fields_cache", "name": "_bound_fields_cache", "type": {".class": "AnyType", "missing_import_name": null, "source_any": null, "type_of_any": 1}}}, "_clean_fields": {".class": "SymbolTableNode", "kind": "Mdef", "node": {".class": "FuncDef", "arg_kinds": [0], "arg_names": ["self"], "flags": [], "fullname": "django.forms.forms.BaseForm._clean_fields", "name": "_clean_fields", "type": null}}, "_clean_form": {".class": "SymbolTableNode", "kind": "Mdef", "node": {".class": "FuncDef", "arg_kinds": [0], "arg_names": ["self"], "flags": [], "fullname": "django.forms.forms.BaseForm._clean_form", "name": "_clean_form", "type": null}}, "_errors": {".class": "SymbolTableNode", "implicit": true, "kind": "Mdef", "node": {".class": "Var", "flags": [], "fullname": "django.forms.forms.BaseForm._errors", "name": "_errors", "type": {".class": "AnyType", "missing_import_name": null, "source_any": null, "type_of_any": 1}}}, "_html_output": {".class": "SymbolTableNode", "kind": "Mdef", "node": {".class": "FuncDef", "arg_kinds": [0, 0, 0, 0, 0, 0], "arg_names": ["self", "normal_row", "error_row", "row_ender", "help_text_html", "errors_on_separate_row"], "flags": [], "fullname": "django.forms.forms.BaseForm._html_output", "name": "_html_output", "type": null}}, "_post_clean": {".class": "SymbolTableNode", "kind": "Mdef", "node": {".class": "FuncDef", "arg_kinds": [0], "arg_names": ["self"], "flags": [], "fullname": "django.forms.forms.BaseForm._post_clean", "name": "_post_clean", "type": null}}, "add_error": {".class": "SymbolTableNode", "kind": "Mdef", "node": {".class": "FuncDef", "arg_kinds": [0, 0, 0], "arg_names": ["self", "field", "error"], "flags": [], "fullname": "django.forms.forms.BaseForm.add_error", "name": "add_error", "type": null}}, "add_initial_prefix": {".class": "SymbolTableNode", "kind": "Mdef", "node": {".class": "FuncDef", "arg_kinds": [0, 0], "arg_names": ["self", "field_name"], "flags": [], "fullname": "django.forms.forms.BaseForm.add_initial_prefix", "name": "add_initial_prefix", "type": null}}, "add_prefix": {".class": "SymbolTableNode", "kind": "Mdef", "node": {".class": "FuncDef", "arg_kinds": [0, 0], "arg_names": ["self", "field_name"], "flags": [], "fullname": "django.forms.forms.BaseForm.add_prefix", "name": "add_prefix", "type": null}}, "as_p": {".class": "SymbolTableNode", "kind": "Mdef", "node": {".class": "FuncDef", "arg_kinds": [0], "arg_names": ["self"], "flags": [], "fullname": "django.forms.forms.BaseForm.as_p", "name": "as_p", "type": null}}, "as_table": {".class": "SymbolTableNode", "kind": "Mdef", "node": {".class": "FuncDef", "arg_kinds": [0], "arg_names": ["self"], "flags": [], "fullname": "django.forms.forms.BaseForm.as_table", "name": "as_table", "type": null}}, "as_ul": {".class": "SymbolTableNode", "kind": "Mdef", "node": {".class": "FuncDef", "arg_kinds": [0], "arg_names": ["self"], "flags": [], "fullname": "django.forms.forms.BaseForm.as_ul", "name": "as_ul", "type": null}}, "auto_id": {".class": "SymbolTableNode", "implicit": true, "kind": "Mdef", "node": {".class": "Var", "flags": [], "fullname": "django.forms.forms.BaseForm.auto_id", "name": "auto_id", "type": {".class": "AnyType", "missing_import_name": null, "source_any": null, "type_of_any": 1}}}, "changed_data": {".class": "SymbolTableNode", "kind": "Mdef", "node": {".class": "Decorator", "func": {".class": "FuncDef", "arg_kinds": [0], "arg_names": ["self"], "flags": ["is_decorated"], "fullname": "django.forms.forms.BaseForm.changed_data", "name": "changed_data", "type": null}, "is_overload": false, "var": {".class": "Var", "flags": ["is_initialized_in_class", "is_ready"], "fullname": null, "name": "changed_data", "type": "django.utils.functional.cached_property"}}}, "clean": {".class": "SymbolTableNode", "kind": "Mdef", "node": {".class": "FuncDef", "arg_kinds": [0], "arg_names": ["self"], "flags": [], "fullname": "django.forms.forms.BaseForm.clean", "name": "clean", "type": null}}, "cleaned_data": {".class": "SymbolTableNode", "implicit": true, "kind": "Mdef", "node": {".class": "Var", "flags": [], "fullname": "django.forms.forms.BaseForm.cleaned_data", "name": "cleaned_data", "type": {".class": "AnyType", "missing_import_name": null, "source_any": null, "type_of_any": 1}}}, "data": {".class": "SymbolTableNode", "implicit": true, "kind": "Mdef", "node": {".class": "Var", "flags": [], "fullname": "django.forms.forms.BaseForm.data", "name": "data", "type": {".class": "AnyType", "missing_import_name": null, "source_any": null, "type_of_any": 1}}}, "default_renderer": {".class": "SymbolTableNode", "kind": "Mdef", "node": {".class": "Var", "flags": ["is_initialized_in_class"], "fullname": "django.forms.forms.BaseForm.default_renderer", "name": "default_renderer", "type": {".class": "NoneType"}}}, "empty_permitted": {".class": "SymbolTableNode", "implicit": true, "kind": "Mdef", "node": {".class": "Var", "flags": [], "fullname": "django.forms.forms.BaseForm.empty_permitted", "name": "empty_permitted", "type": {".class": "AnyType", "missing_import_name": null, "source_any": null, "type_of_any": 1}}}, "error_class": {".class": "SymbolTableNode", "implicit": true, "kind": "Mdef", "node": {".class": "Var", "flags": [], "fullname": "django.forms.forms.BaseForm.error_class", "name": "error_class", "type": {".class": "AnyType", "missing_import_name": null, "source_any": null, "type_of_any": 1}}}, "errors": {".class": "SymbolTableNode", "kind": "Mdef", "node": {".class": "Decorator", "func": {".class": "FuncDef", "arg_kinds": [0], "arg_names": ["self"], "flags": ["is_property", "is_decorated"], "fullname": "django.forms.forms.BaseForm.errors", "name": "errors", "type": null}, "is_overload": false, "var": {".class": "Var", "flags": ["is_initialized_in_class", "is_property", "is_ready"], "fullname": null, "name": "errors", "type": {".class": "CallableType", "arg_kinds": [0], "arg_names": ["self"], "arg_types": ["django.forms.forms.BaseForm"], "bound_args": [], "def_extras": {}, "fallback": "builtins.function", "implicit": true, "is_ellipsis_args": false, "name": "errors of BaseForm", "ret_type": {".class": "AnyType", "missing_import_name": null, "source_any": null, "type_of_any": 1}, "variables": []}}}}, "field_order": {".class": "SymbolTableNode", "kind": "Mdef", "node": {".class": "Var", "flags": ["is_initialized_in_class"], "fullname": "django.forms.forms.BaseForm.field_order", "name": "field_order", "type": {".class": "NoneType"}}}, "fields": {".class": "SymbolTableNode", "implicit": true, "kind": "Mdef", "node": {".class": "Var", "flags": [], "fullname": "django.forms.forms.BaseForm.fields", "name": "fields", "type": {".class": "AnyType", "missing_import_name": null, "source_any": null, "type_of_any": 1}}}, "files": {".class": "SymbolTableNode", "implicit": true, "kind": "Mdef", "node": {".class": "Var", "flags": [], "fullname": "django.forms.forms.BaseForm.files", "name": "files", "type": {".class": "AnyType", "missing_import_name": null, "source_any": null, "type_of_any": 1}}}, "full_clean": {".class": "SymbolTableNode", "kind": "Mdef", "node": {".class": "FuncDef", "arg_kinds": [0], "arg_names": ["self"], "flags": [], "fullname": "django.forms.forms.BaseForm.full_clean", "name": "full_clean", "type": null}}, "get_initial_for_field": {".class": "SymbolTableNode", "kind": "Mdef", "node": {".class": "FuncDef", "arg_kinds": [0, 0, 0], "arg_names": ["self", "field", "field_name"], "flags": [], "fullname": "django.forms.forms.BaseForm.get_initial_for_field", "name": "get_initial_for_field", "type": null}}, "has_changed": {".class": "SymbolTableNode", "kind": "Mdef", "node": {".class": "FuncDef", "arg_kinds": [0], "arg_names": ["self"], "flags": [], "fullname": "django.forms.forms.BaseForm.has_changed", "name": "has_changed", "type": null}}, "has_error": {".class": "SymbolTableNode", "kind": "Mdef", "node": {".class": "FuncDef", "arg_kinds": [0, 0, 1], "arg_names": ["self", "field", "code"], "flags": [], "fullname": "django.forms.forms.BaseForm.has_error", "name": "has_error", "type": null}}, "hidden_fields": {".class": "SymbolTableNode", "kind": "Mdef", "node": {".class": "FuncDef", "arg_kinds": [0], "arg_names": ["self"], "flags": [], "fullname": "django.forms.forms.BaseForm.hidden_fields", "name": "hidden_fields", "type": null}}, "initial": {".class": "SymbolTableNode", "implicit": true, "kind": "Mdef", "node": {".class": "Var", "flags": [], "fullname": "django.forms.forms.BaseForm.initial", "name": "initial", "type": {".class": "AnyType", "missing_import_name": null, "source_any": null, "type_of_any": 1}}}, "is_bound": {".class": "SymbolTableNode", "implicit": true, "kind": "Mdef", "node": {".class": "Var", "flags": [], "fullname": "django.forms.forms.BaseForm.is_bound", "name": "is_bound", "type": {".class": "AnyType", "missing_import_name": null, "source_any": null, "type_of_any": 1}}}, "is_multipart": {".class": "SymbolTableNode", "kind": "Mdef", "node": {".class": "FuncDef", "arg_kinds": [0], "arg_names": ["self"], "flags": [], "fullname": "django.forms.forms.BaseForm.is_multipart", "name": "is_multipart", "type": null}}, "is_valid": {".class": "SymbolTableNode", "kind": "Mdef", "node": {".class": "FuncDef", "arg_kinds": [0], "arg_names": ["self"], "flags": [], "fullname": "django.forms.forms.BaseForm.is_valid", "name": "is_valid", "type": null}}, "label_suffix": {".class": "SymbolTableNode", "implicit": true, "kind": "Mdef", "node": {".class": "Var", "flags": [], "fullname": "django.forms.forms.BaseForm.label_suffix", "name": "label_suffix", "type": {".class": "AnyType", "missing_import_name": null, "source_any": null, "type_of_any": 1}}}, "media": {".class": "SymbolTableNode", "kind": "Mdef", "node": {".class": "Decorator", "func": {".class": "FuncDef", "arg_kinds": [0], "arg_names": ["self"], "flags": ["is_property", "is_decorated"], "fullname": "django.forms.forms.BaseForm.media", "name": "media", "type": null}, "is_overload": false, "var": {".class": "Var", "flags": ["is_initialized_in_class", "is_property", "is_ready"], "fullname": null, "name": "media", "type": {".class": "CallableType", "arg_kinds": [0], "arg_names": ["self"], "arg_types": ["django.forms.forms.BaseForm"], "bound_args": [], "def_extras": {}, "fallback": "builtins.function", "implicit": true, "is_ellipsis_args": false, "name": "media of BaseForm", "ret_type": {".class": "AnyType", "missing_import_name": null, "source_any": null, "type_of_any": 1}, "variables": []}}}}, "non_field_errors": {".class": "SymbolTableNode", "kind": "Mdef", "node": {".class": "FuncDef", "arg_kinds": [0], "arg_names": ["self"], "flags": [], "fullname": "django.forms.forms.BaseForm.non_field_errors", "name": "non_field_errors", "type": null}}, "order_fields": {".class": "SymbolTableNode", "kind": "Mdef", "node": {".class": "FuncDef", "arg_kinds": [0, 0], "arg_names": ["self", "field_order"], "flags": [], "fullname": "django.forms.forms.BaseForm.order_fields", "name": "order_fields", "type": null}}, "prefix": {".class": "SymbolTableNode", "kind": "Mdef", "node": {".class": "Var", "flags": ["is_initialized_in_class"], "fullname": "django.forms.forms.BaseForm.prefix", "name": "prefix", "type": {".class": "NoneType"}}}, "renderer": {".class": "SymbolTableNode", "implicit": true, "kind": "Mdef", "node": {".class": "Var", "flags": [], "fullname": "django.forms.forms.BaseForm.renderer", "name": "renderer", "type": {".class": "AnyType", "missing_import_name": null, "source_any": null, "type_of_any": 1}}}, "use_required_attribute": {".class": "SymbolTableNode", "kind": "Mdef", "node": {".class": "Var", "flags": ["is_initialized_in_class"], "fullname": "django.forms.forms.BaseForm.use_required_attribute", "name": "use_required_attribute", "type": "builtins.bool"}}, "visible_fields": {".class": "SymbolTableNode", "kind": "Mdef", "node": {".class": "FuncDef", "arg_kinds": [0], "arg_names": ["self"], "flags": [], "fullname": "django.forms.forms.BaseForm.visible_fields", "name": "visible_fields", "type": null}}}, "tuple_type": null, "type_vars": [], "typeddict_type": null}}, "DeclarativeFieldsMetaclass": {".class": "SymbolTableNode", "kind": "Gdef", "module_public": false, "node": {".class": "TypeInfo", "_promote": null, "abstract_attributes": [], "bases": ["django.forms.widgets.MediaDefiningClass"], "declared_metaclass": null, "defn": {".class": "ClassDef", "fullname": "django.forms.forms.DeclarativeFieldsMetaclass", "name": "DeclarativeFieldsMetaclass", "type_vars": []}, "flags": [], "fullname": "django.forms.forms.DeclarativeFieldsMetaclass", "metaclass_type": null, "metadata": {}, "module_name": "django.forms.forms", "mro": ["django.forms.forms.DeclarativeFieldsMetaclass", "django.forms.widgets.MediaDefiningClass", "builtins.type", "builtins.object"], "names": {".class": "SymbolTable", "__new__": {".class": "SymbolTableNode", "kind": "Mdef", "node": {".class": "FuncDef", "arg_kinds": [0, 0, 0, 0], "arg_names": ["mcs", "name", "bases", "attrs"], "flags": [], "fullname": "django.forms.forms.DeclarativeFieldsMetaclass.__new__", "name": "__new__", "type": null}}}, "tuple_type": null, "type_vars": [], "typeddict_type": null}}, "ErrorDict": {".class": "SymbolTableNode", "cross_ref": "django.forms.utils.ErrorDict", "kind": "Gdef", "module_public": false}, "ErrorList": {".class": "SymbolTableNode", "cross_ref": "django.forms.utils.ErrorList", "kind": "Gdef", "module_public": false}, "Field": {".class": "SymbolTableNode", "cross_ref": "django.forms.fields.Field", "kind": "Gdef", "module_public": false}, "FileField": {".class": "SymbolTableNode", "cross_ref": "django.forms.fields.FileField", "kind": "Gdef", "module_public": false}, "Form": {".class": "SymbolTableNode", "kind": "Gdef", "node": {".class": "TypeInfo", "_promote": null, "abstract_attributes": [], "bases": ["django.forms.forms.BaseForm"], "declared_metaclass": "django.forms.forms.DeclarativeFieldsMetaclass", "defn": {".class": "ClassDef", "fullname": "django.forms.forms.Form", "name": "Form", "type_vars": []}, "flags": [], "fullname": "django.forms.forms.Form", "metaclass_type": "django.forms.forms.DeclarativeFieldsMetaclass", "metadata": {}, "module_name": "django.forms.forms", "mro": ["django.forms.forms.Form", "django.forms.forms.BaseForm", "builtins.object"], "names": {".class": "SymbolTable"}, "tuple_type": null, "type_vars": [], "typeddict_type": null}}, "Media": {".class": "SymbolTableNode", "cross_ref": "django.forms.widgets.Media", "kind": "Gdef", "module_public": false}, "MediaDefiningClass": {".class": "SymbolTableNode", "cross_ref": "django.forms.widgets.MediaDefiningClass", "kind": "Gdef", "module_public": false}, "MultiValueDict": {".class": "SymbolTableNode", "cross_ref": "django.utils.datastructures.MultiValueDict", "kind": "Gdef", "module_public": false}, "NON_FIELD_ERRORS": {".class": "SymbolTableNode", "cross_ref": "django.core.exceptions.NON_FIELD_ERRORS", "kind": "Gdef", "module_public": false}, "ValidationError": {".class": "SymbolTableNode", "cross_ref": "django.core.exceptions.ValidationError", "kind": "Gdef", "module_public": false}, "_": {".class": "SymbolTableNode", "cross_ref": "django.utils.translation.gettext", "kind": "Gdef", "module_public": false}, "__all__": {".class": "SymbolTableNode", "kind": "Gdef", "module_public": false, "node": {".class": "Var", "flags": [], "fullname": "django.forms.forms.__all__", "name": "__all__", "type": {".class": "TupleType", "implicit": false, "items": ["builtins.str", "builtins.str"], "partial_fallback": {".class": "Instance", "args": [{".class": "AnyType", "missing_import_name": null, "source_any": null, "type_of_any": 6}], "type_ref": "builtins.tuple"}}}}, "__doc__": {".class": "SymbolTableNode", "kind": "Gdef", "module_public": false, "node": {".class": "Var", "flags": ["is_ready"], "fullname": "django.forms.forms.__doc__", "name": "__doc__", "type": "builtins.str"}}, "__file__": {".class": "SymbolTableNode", "kind": "Gdef", "module_public": false, "node": {".class": "Var", "flags": ["is_ready"], "fullname": "django.forms.forms.__file__", "name": "__file__", "type": "builtins.str"}}, "__name__": {".class": "SymbolTableNode", "kind": "Gdef", "module_public": false, "node": {".class": "Var", "flags": ["is_ready"], "fullname": "django.forms.forms.__name__", "name": "__name__", "type": "builtins.str"}}, "__package__": {".class": "SymbolTableNode", "kind": "Gdef", "module_public": false, "node": {".class": "Var", "flags": ["is_ready"], "fullname": "django.forms.forms.__package__", "name": "__package__", "type": "builtins.str"}}, "cached_property": {".class": "SymbolTableNode", "cross_ref": "django.utils.functional.cached_property", "kind": "Gdef", "module_public": false}, "conditional_escape": {".class": "SymbolTableNode", "cross_ref": "django.utils.html.conditional_escape", "kind": "Gdef", "module_public": false}, "copy": {".class": "SymbolTableNode", "cross_ref": "copy", "kind": "Gdef", "module_public": false}, "get_default_renderer": {".class": "SymbolTableNode", "cross_ref": "django.forms.renderers.get_default_renderer", "kind": "Gdef", "module_public": false}, "html_safe": {".class": "SymbolTableNode", "cross_ref": "django.utils.html.html_safe", "kind": "Gdef", "module_public": false}, "mark_safe": {".class": "SymbolTableNode", "cross_ref": "django.utils.safestring.mark_safe", "kind": "Gdef", "module_public": false}}, "path": "/home/ibrahim/opensrc/django/django/forms/forms.py"}