{".class": "MypyFile", "_fullname": "django.template.exceptions", "is_partial_stub_package": false, "is_stub": false, "names": {".class": "SymbolTable", "TemplateDoesNotExist": {".class": "SymbolTableNode", "kind": "Gdef", "node": {".class": "TypeInfo", "_promote": null, "abstract_attributes": [], "bases": ["builtins.Exception"], "declared_metaclass": null, "defn": {".class": "ClassDef", "fullname": "django.template.exceptions.TemplateDoesNotExist", "name": "TemplateDoesNotExist", "type_vars": []}, "flags": [], "fullname": "django.template.exceptions.TemplateDoesNotExist", "metaclass_type": null, "metadata": {}, "module_name": "django.template.exceptions", "mro": ["django.template.exceptions.TemplateDoesNotExist", "builtins.Exception", "builtins.BaseException", "builtins.object"], "names": {".class": "SymbolTable", "__init__": {".class": "SymbolTableNode", "kind": "Mdef", "node": {".class": "FuncDef", "arg_kinds": [0, 0, 1, 1, 1], "arg_names": ["self", "msg", "tried", "backend", "chain"], "flags": [], "fullname": "django.template.exceptions.TemplateDoesNotExist.__init__", "name": "__init__", "type": null}}, "backend": {".class": "SymbolTableNode", "implicit": true, "kind": "Mdef", "node": {".class": "Var", "flags": [], "fullname": "django.template.exceptions.TemplateDoesNotExist.backend", "name": "backend", "type": {".class": "AnyType", "missing_import_name": null, "source_any": null, "type_of_any": 1}}}, "chain": {".class": "SymbolTableNode", "implicit": true, "kind": "Mdef", "node": {".class": "Var", "flags": [], "fullname": "django.template.exceptions.TemplateDoesNotExist.chain", "name": "chain", "type": {".class": "AnyType", "missing_import_name": null, "source_any": null, "type_of_any": 1}}}, "tried": {".class": "SymbolTableNode", "implicit": true, "kind": "Mdef", "node": {".class": "Var", "flags": [], "fullname": "django.template.exceptions.TemplateDoesNotExist.tried", "name": "tried", "type": {".class": "AnyType", "missing_import_name": null, "source_any": null, "type_of_any": 1}}}}, "tuple_type": null, "type_vars": [], "typeddict_type": null}}, "TemplateSyntaxError": {".class": "SymbolTableNode", "kind": "Gdef", "node": {".class": "TypeInfo", "_promote": null, "abstract_attributes": [], "bases": ["builtins.Exception"], "declared_metaclass": null, "defn": {".class": "ClassDef", "fullname": "django.template.exceptions.TemplateSyntaxError", "name": "TemplateSyntaxError", "type_vars": []}, "flags": [], "fullname": "django.template.exceptions.TemplateSyntaxError", "metaclass_type": null, "metadata": {}, "module_name": "django.template.exceptions", "mro": ["django.template.exceptions.TemplateSyntaxError", "builtins.Exception", "builtins.BaseException", "builtins.object"], "names": {".class": "SymbolTable"}, "tuple_type": null, "type_vars": [], "typeddict_type": null}}, "__doc__": {".class": "SymbolTableNode", "kind": "Gdef", "node": {".class": "Var", "flags": ["is_ready"], "fullname": "django.template.exceptions.__doc__", "name": "__doc__", "type": "builtins.str"}}, "__file__": {".class": "SymbolTableNode", "kind": "Gdef", "node": {".class": "Var", "flags": ["is_ready"], "fullname": "django.template.exceptions.__file__", "name": "__file__", "type": "builtins.str"}}, "__name__": {".class": "SymbolTableNode", "kind": "Gdef", "node": {".class": "Var", "flags": ["is_ready"], "fullname": "django.template.exceptions.__name__", "name": "__name__", "type": "builtins.str"}}, "__package__": {".class": "SymbolTableNode", "kind": "Gdef", "node": {".class": "Var", "flags": ["is_ready"], "fullname": "django.template.exceptions.__package__", "name": "__package__", "type": "builtins.str"}}}, "path": "/home/ibrahim/opensrc/django/django/template/exceptions.py"}