{".class": "MypyFile", "_fullname": "django.core.checks.security.csrf", "is_partial_stub_package": false, "is_stub": false, "names": {".class": "SymbolTable", "Tags": {".class": "SymbolTableNode", "cross_ref": "django.core.checks.registry.Tags", "kind": "Gdef"}, "W003": {".class": "SymbolTableNode", "kind": "Gdef", "node": {".class": "Var", "flags": [], "fullname": "django.core.checks.security.csrf.W003", "name": "W003", "type": "django.core.checks.messages.Warning"}}, "W016": {".class": "SymbolTableNode", "kind": "Gdef", "node": {".class": "Var", "flags": [], "fullname": "django.core.checks.security.csrf.W016", "name": "W016", "type": "django.core.checks.messages.Warning"}}, "Warning": {".class": "SymbolTableNode", "cross_ref": "django.core.checks.messages.Warning", "kind": "Gdef"}, "__doc__": {".class": "SymbolTableNode", "kind": "Gdef", "node": {".class": "Var", "flags": ["is_ready"], "fullname": "django.core.checks.security.csrf.__doc__", "name": "__doc__", "type": "builtins.str"}}, "__file__": {".class": "SymbolTableNode", "kind": "Gdef", "node": {".class": "Var", "flags": ["is_ready"], "fullname": "django.core.checks.security.csrf.__file__", "name": "__file__", "type": "builtins.str"}}, "__name__": {".class": "SymbolTableNode", "kind": "Gdef", "node": {".class": "Var", "flags": ["is_ready"], "fullname": "django.core.checks.security.csrf.__name__", "name": "__name__", "type": "builtins.str"}}, "__package__": {".class": "SymbolTableNode", "kind": "Gdef", "node": {".class": "Var", "flags": ["is_ready"], "fullname": "django.core.checks.security.csrf.__package__", "name": "__package__", "type": "builtins.str"}}, "_csrf_middleware": {".class": "SymbolTableNode", "kind": "Gdef", "node": {".class": "FuncDef", "arg_kinds": [], "arg_names": [], "flags": [], "fullname": "django.core.checks.security.csrf._csrf_middleware", "name": "_csrf_middleware", "type": null}}, "check_csrf_cookie_secure": {".class": "SymbolTableNode", "kind": "Gdef", "node": {".class": "Decorator", "func": {".class": "FuncDef", "arg_kinds": [0, 4], "arg_names": ["app_configs", "kwargs"], "flags": ["is_decorated"], "fullname": "django.core.checks.security.csrf.check_csrf_cookie_secure", "name": "check_csrf_cookie_secure", "type": null}, "is_overload": false, "var": {".class": "Var", "flags": ["is_ready"], "fullname": null, "name": "check_csrf_cookie_secure", "type": {".class": "AnyType", "missing_import_name": null, "source_any": {".class": "AnyType", "missing_import_name": null, "source_any": null, "type_of_any": 1}, "type_of_any": 7}}}}, "check_csrf_middleware": {".class": "SymbolTableNode", "kind": "Gdef", "node": {".class": "Decorator", "func": {".class": "FuncDef", "arg_kinds": [0, 4], "arg_names": ["app_configs", "kwargs"], "flags": ["is_decorated"], "fullname": "django.core.checks.security.csrf.check_csrf_middleware", "name": "check_csrf_middleware", "type": null}, "is_overload": false, "var": {".class": "Var", "flags": ["is_ready"], "fullname": null, "name": "check_csrf_middleware", "type": {".class": "AnyType", "missing_import_name": null, "source_any": {".class": "AnyType", "missing_import_name": null, "source_any": null, "type_of_any": 1}, "type_of_any": 7}}}}, "register": {".class": "SymbolTableNode", "cross_ref": "django.core.checks.registry.register", "kind": "Gdef"}, "settings": {".class": "SymbolTableNode", "cross_ref": "django.conf.settings", "kind": "Gdef"}}, "path": "/home/ibrahim/opensrc/django/django/core/checks/security/csrf.py"}