{".class": "MypyFile", "_fullname": "django.urls.resolvers", "is_partial_stub_package": false, "is_stub": false, "names": {".class": "SymbolTable", "CheckURLMixin": {".class": "SymbolTableNode", "kind": "Gdef", "node": {".class": "TypeInfo", "_promote": null, "abstract_attributes": [], "bases": ["builtins.object"], "declared_metaclass": null, "defn": {".class": "ClassDef", "fullname": "django.urls.resolvers.CheckURLMixin", "name": "CheckURLMixin", "type_vars": []}, "flags": [], "fullname": "django.urls.resolvers.CheckURLMixin", "metaclass_type": null, "metadata": {}, "module_name": "django.urls.resolvers", "mro": ["django.urls.resolvers.CheckURLMixin", "builtins.object"], "names": {".class": "SymbolTable", "_check_pattern_startswith_slash": {".class": "SymbolTableNode", "kind": "Mdef", "node": {".class": "FuncDef", "arg_kinds": [0], "arg_names": ["self"], "flags": [], "fullname": "django.urls.resolvers.CheckURLMixin._check_pattern_startswith_slash", "name": "_check_pattern_startswith_slash", "type": null}}, "describe": {".class": "SymbolTableNode", "kind": "Mdef", "node": {".class": "FuncDef", "arg_kinds": [0], "arg_names": ["self"], "flags": [], "fullname": "django.urls.resolvers.CheckURLMixin.describe", "name": "describe", "type": null}}}, "tuple_type": null, "type_vars": [], "typeddict_type": null}}, "Error": {".class": "SymbolTableNode", "cross_ref": "django.core.checks.messages.Error", "kind": "Gdef"}, "ImproperlyConfigured": {".class": "SymbolTableNode", "cross_ref": "django.core.exceptions.ImproperlyConfigured", "kind": "Gdef"}, "Local": {".class": "SymbolTableNode", "kind": "Gdef", "node": {".class": "Var", "flags": ["is_suppressed_import", "is_ready"], "fullname": "django.urls.resolvers.Local", "name": "Local", "type": {".class": "AnyType", "missing_import_name": "django.urls.resolvers.Local", "source_any": null, "type_of_any": 3}}}, "LocalePrefixPattern": {".class": "SymbolTableNode", "kind": "Gdef", "node": {".class": "TypeInfo", "_promote": null, "abstract_attributes": [], "bases": ["builtins.object"], "declared_metaclass": null, "defn": {".class": "ClassDef", "fullname": "django.urls.resolvers.LocalePrefixPattern", "name": "LocalePrefixPattern", "type_vars": []}, "flags": [], "fullname": "django.urls.resolvers.LocalePrefixPattern", "metaclass_type": null, "metadata": {}, "module_name": "django.urls.resolvers", "mro": ["django.urls.resolvers.LocalePrefixPattern", "builtins.object"], "names": {".class": "SymbolTable", "__init__": {".class": "SymbolTableNode", "kind": "Mdef", "node": {".class": "FuncDef", "arg_kinds": [0, 1], "arg_names": ["self", "prefix_default_language"], "flags": [], "fullname": "django.urls.resolvers.LocalePrefixPattern.__init__", "name": "__init__", "type": null}}, "__str__": {".class": "SymbolTableNode", "kind": "Mdef", "node": {".class": "FuncDef", "arg_kinds": [0], "arg_names": ["self"], "flags": [], "fullname": "django.urls.resolvers.LocalePrefixPattern.__str__", "name": "__str__", "type": null}}, "check": {".class": "SymbolTableNode", "kind": "Mdef", "node": {".class": "FuncDef", "arg_kinds": [0], "arg_names": ["self"], "flags": [], "fullname": "django.urls.resolvers.LocalePrefixPattern.check", "name": "check", "type": null}}, "converters": {".class": "SymbolTableNode", "implicit": true, "kind": "Mdef", "node": {".class": "Var", "flags": [], "fullname": "django.urls.resolvers.LocalePrefixPattern.converters", "name": "converters", "type": {".class": "AnyType", "missing_import_name": null, "source_any": null, "type_of_any": 1}}}, "describe": {".class": "SymbolTableNode", "kind": "Mdef", "node": {".class": "FuncDef", "arg_kinds": [0], "arg_names": ["self"], "flags": [], "fullname": "django.urls.resolvers.LocalePrefixPattern.describe", "name": "describe", "type": null}}, "language_prefix": {".class": "SymbolTableNode", "kind": "Mdef", "node": {".class": "Decorator", "func": {".class": "FuncDef", "arg_kinds": [0], "arg_names": ["self"], "flags": ["is_property", "is_decorated"], "fullname": "django.urls.resolvers.LocalePrefixPattern.language_prefix", "name": "language_prefix", "type": null}, "is_overload": false, "var": {".class": "Var", "flags": ["is_initialized_in_class", "is_property", "is_ready"], "fullname": null, "name": "language_prefix", "type": {".class": "CallableType", "arg_kinds": [0], "arg_names": ["self"], "arg_types": ["django.urls.resolvers.LocalePrefixPattern"], "bound_args": [], "def_extras": {}, "fallback": "builtins.function", "implicit": true, "is_ellipsis_args": false, "name": "language_prefix of LocalePrefixPattern", "ret_type": {".class": "AnyType", "missing_import_name": null, "source_any": null, "type_of_any": 1}, "variables": []}}}}, "match": {".class": "SymbolTableNode", "kind": "Mdef", "node": {".class": "FuncDef", "arg_kinds": [0, 0], "arg_names": ["self", "path"], "flags": [], "fullname": "django.urls.resolvers.LocalePrefixPattern.match", "name": "match", "type": null}}, "prefix_default_language": {".class": "SymbolTableNode", "implicit": true, "kind": "Mdef", "node": {".class": "Var", "flags": [], "fullname": "django.urls.resolvers.LocalePrefixPattern.prefix_default_language", "name": "prefix_default_language", "type": {".class": "AnyType", "missing_import_name": null, "source_any": null, "type_of_any": 1}}}, "regex": {".class": "SymbolTableNode", "kind": "Mdef", "node": {".class": "Decorator", "func": {".class": "FuncDef", "arg_kinds": [0], "arg_names": ["self"], "flags": ["is_property", "is_decorated"], "fullname": "django.urls.resolvers.LocalePrefixPattern.regex", "name": "regex", "type": null}, "is_overload": false, "var": {".class": "Var", "flags": ["is_initialized_in_class", "is_property", "is_ready"], "fullname": null, "name": "regex", "type": {".class": "CallableType", "arg_kinds": [0], "arg_names": ["self"], "arg_types": ["django.urls.resolvers.LocalePrefixPattern"], "bound_args": [], "def_extras": {}, "fallback": "builtins.function", "implicit": true, "is_ellipsis_args": false, "name": "regex of LocalePrefixPattern", "ret_type": {".class": "AnyType", "missing_import_name": null, "source_any": null, "type_of_any": 1}, "variables": []}}}}}, "tuple_type": null, "type_vars": [], "typeddict_type": null}}, "LocaleRegexDescriptor": {".class": "SymbolTableNode", "kind": "Gdef", "node": {".class": "TypeInfo", "_promote": null, "abstract_attributes": [], "bases": ["builtins.object"], "declared_metaclass": null, "defn": {".class": "ClassDef", "fullname": "django.urls.resolvers.LocaleRegexDescriptor", "name": "LocaleRegexDescriptor", "type_vars": []}, "flags": [], "fullname": "django.urls.resolvers.LocaleRegexDescriptor", "metaclass_type": null, "metadata": {}, "module_name": "django.urls.resolvers", "mro": ["django.urls.resolvers.LocaleRegexDescriptor", "builtins.object"], "names": {".class": "SymbolTable", "__get__": {".class": "SymbolTableNode", "kind": "Mdef", "node": {".class": "FuncDef", "arg_kinds": [0, 0, 1], "arg_names": ["self", "instance", "cls"], "flags": [], "fullname": "django.urls.resolvers.LocaleRegexDescriptor.__get__", "name": "__get__", "type": null}}, "__init__": {".class": "SymbolTableNode", "kind": "Mdef", "node": {".class": "FuncDef", "arg_kinds": [0, 0], "arg_names": ["self", "attr"], "flags": [], "fullname": "django.urls.resolvers.LocaleRegexDescriptor.__init__", "name": "__init__", "type": null}}, "attr": {".class": "SymbolTableNode", "implicit": true, "kind": "Mdef", "node": {".class": "Var", "flags": [], "fullname": "django.urls.resolvers.LocaleRegexDescriptor.attr", "name": "attr", "type": {".class": "AnyType", "missing_import_name": null, "source_any": null, "type_of_any": 1}}}}, "tuple_type": null, "type_vars": [], "typeddict_type": null}}, "MultiValueDict": {".class": "SymbolTableNode", "cross_ref": "django.utils.datastructures.MultiValueDict", "kind": "Gdef"}, "NoReverseMatch": {".class": "SymbolTableNode", "cross_ref": "django.urls.exceptions.NoReverseMatch", "kind": "Gdef"}, "RFC3986_SUBDELIMS": {".class": "SymbolTableNode", "cross_ref": "django.utils.http.RFC3986_SUBDELIMS", "kind": "Gdef"}, "RegexPattern": {".class": "SymbolTableNode", "kind": "Gdef", "node": {".class": "TypeInfo", "_promote": null, "abstract_attributes": [], "bases": ["django.urls.resolvers.CheckURLMixin"], "declared_metaclass": null, "defn": {".class": "ClassDef", "fullname": "django.urls.resolvers.RegexPattern", "name": "RegexPattern", "type_vars": []}, "flags": [], "fullname": "django.urls.resolvers.RegexPattern", "metaclass_type": null, "metadata": {}, "module_name": "django.urls.resolvers", "mro": ["django.urls.resolvers.RegexPattern", "django.urls.resolvers.CheckURLMixin", "builtins.object"], "names": {".class": "SymbolTable", "__init__": {".class": "SymbolTableNode", "kind": "Mdef", "node": {".class": "FuncDef", "arg_kinds": [0, 0, 1, 1], "arg_names": ["self", "regex", "name", "is_endpoint"], "flags": [], "fullname": "django.urls.resolvers.RegexPattern.__init__", "name": "__init__", "type": null}}, "__str__": {".class": "SymbolTableNode", "kind": "Mdef", "node": {".class": "FuncDef", "arg_kinds": [0], "arg_names": ["self"], "flags": [], "fullname": "django.urls.resolvers.RegexPattern.__str__", "name": "__str__", "type": null}}, "_check_include_trailing_dollar": {".class": "SymbolTableNode", "kind": "Mdef", "node": {".class": "FuncDef", "arg_kinds": [0], "arg_names": ["self"], "flags": [], "fullname": "django.urls.resolvers.RegexPattern._check_include_trailing_dollar", "name": "_check_include_trailing_dollar", "type": null}}, "_compile": {".class": "SymbolTableNode", "kind": "Mdef", "node": {".class": "FuncDef", "arg_kinds": [0, 0], "arg_names": ["self", "regex"], "flags": [], "fullname": "django.urls.resolvers.RegexPattern._compile", "name": "_compile", "type": null}}, "_is_endpoint": {".class": "SymbolTableNode", "implicit": true, "kind": "Mdef", "node": {".class": "Var", "flags": [], "fullname": "django.urls.resolvers.RegexPattern._is_endpoint", "name": "_is_endpoint", "type": {".class": "AnyType", "missing_import_name": null, "source_any": null, "type_of_any": 1}}}, "_regex": {".class": "SymbolTableNode", "implicit": true, "kind": "Mdef", "node": {".class": "Var", "flags": [], "fullname": "django.urls.resolvers.RegexPattern._regex", "name": "_regex", "type": {".class": "AnyType", "missing_import_name": null, "source_any": null, "type_of_any": 1}}}, "_regex_dict": {".class": "SymbolTableNode", "implicit": true, "kind": "Mdef", "node": {".class": "Var", "flags": [], "fullname": "django.urls.resolvers.RegexPattern._regex_dict", "name": "_regex_dict", "type": {".class": "AnyType", "missing_import_name": null, "source_any": null, "type_of_any": 1}}}, "check": {".class": "SymbolTableNode", "kind": "Mdef", "node": {".class": "FuncDef", "arg_kinds": [0], "arg_names": ["self"], "flags": [], "fullname": "django.urls.resolvers.RegexPattern.check", "name": "check", "type": null}}, "converters": {".class": "SymbolTableNode", "implicit": true, "kind": "Mdef", "node": {".class": "Var", "flags": [], "fullname": "django.urls.resolvers.RegexPattern.converters", "name": "converters", "type": {".class": "AnyType", "missing_import_name": null, "source_any": null, "type_of_any": 1}}}, "match": {".class": "SymbolTableNode", "kind": "Mdef", "node": {".class": "FuncDef", "arg_kinds": [0, 0], "arg_names": ["self", "path"], "flags": [], "fullname": "django.urls.resolvers.RegexPattern.match", "name": "match", "type": null}}, "name": {".class": "SymbolTableNode", "implicit": true, "kind": "Mdef", "node": {".class": "Var", "flags": [], "fullname": "django.urls.resolvers.RegexPattern.name", "name": "name", "type": {".class": "AnyType", "missing_import_name": null, "source_any": null, "type_of_any": 1}}}, "regex": {".class": "SymbolTableNode", "kind": "Mdef", "node": {".class": "Var", "flags": ["is_initialized_in_class"], "fullname": "django.urls.resolvers.RegexPattern.regex", "name": "regex", "type": "django.urls.resolvers.LocaleRegexDescriptor"}}}, "tuple_type": null, "type_vars": [], "typeddict_type": null}}, "Resolver404": {".class": "SymbolTableNode", "cross_ref": "django.urls.exceptions.Resolver404", "kind": "Gdef"}, "ResolverMatch": {".class": "SymbolTableNode", "kind": "Gdef", "node": {".class": "TypeInfo", "_promote": null, "abstract_attributes": [], "bases": ["builtins.object"], "declared_metaclass": null, "defn": {".class": "ClassDef", "fullname": "django.urls.resolvers.ResolverMatch", "name": "ResolverMatch", "type_vars": []}, "flags": [], "fullname": "django.urls.resolvers.ResolverMatch", "metaclass_type": null, "metadata": {}, "module_name": "django.urls.resolvers", "mro": ["django.urls.resolvers.ResolverMatch", "builtins.object"], "names": {".class": "SymbolTable", "__getitem__": {".class": "SymbolTableNode", "kind": "Mdef", "node": {".class": "FuncDef", "arg_kinds": [0, 0], "arg_names": ["self", "index"], "flags": [], "fullname": "django.urls.resolvers.ResolverMatch.__getitem__", "name": "__getitem__", "type": null}}, "__init__": {".class": "SymbolTableNode", "kind": "Mdef", "node": {".class": "FuncDef", "arg_kinds": [0, 0, 0, 0, 1, 1, 1, 1], "arg_names": ["self", "func", "args", "kwargs", "url_name", "app_names", "namespaces", "route"], "flags": [], "fullname": "django.urls.resolvers.ResolverMatch.__init__", "name": "__init__", "type": null}}, "__repr__": {".class": "SymbolTableNode", "kind": "Mdef", "node": {".class": "FuncDef", "arg_kinds": [0], "arg_names": ["self"], "flags": [], "fullname": "django.urls.resolvers.ResolverMatch.__repr__", "name": "__repr__", "type": null}}, "_func_path": {".class": "SymbolTableNode", "implicit": true, "kind": "Mdef", "node": {".class": "Var", "flags": [], "fullname": "django.urls.resolvers.ResolverMatch._func_path", "name": "_func_path", "type": {".class": "AnyType", "missing_import_name": null, "source_any": null, "type_of_any": 1}}}, "app_name": {".class": "SymbolTableNode", "implicit": true, "kind": "Mdef", "node": {".class": "Var", "flags": [], "fullname": "django.urls.resolvers.ResolverMatch.app_name", "name": "app_name", "type": {".class": "AnyType", "missing_import_name": null, "source_any": null, "type_of_any": 1}}}, "app_names": {".class": "SymbolTableNode", "implicit": true, "kind": "Mdef", "node": {".class": "Var", "flags": [], "fullname": "django.urls.resolvers.ResolverMatch.app_names", "name": "app_names", "type": {".class": "AnyType", "missing_import_name": null, "source_any": null, "type_of_any": 1}}}, "args": {".class": "SymbolTableNode", "implicit": true, "kind": "Mdef", "node": {".class": "Var", "flags": [], "fullname": "django.urls.resolvers.ResolverMatch.args", "name": "args", "type": {".class": "AnyType", "missing_import_name": null, "source_any": null, "type_of_any": 1}}}, "func": {".class": "SymbolTableNode", "implicit": true, "kind": "Mdef", "node": {".class": "Var", "flags": [], "fullname": "django.urls.resolvers.ResolverMatch.func", "name": "func", "type": {".class": "AnyType", "missing_import_name": null, "source_any": null, "type_of_any": 1}}}, "kwargs": {".class": "SymbolTableNode", "implicit": true, "kind": "Mdef", "node": {".class": "Var", "flags": [], "fullname": "django.urls.resolvers.ResolverMatch.kwargs", "name": "kwargs", "type": {".class": "AnyType", "missing_import_name": null, "source_any": null, "type_of_any": 1}}}, "namespace": {".class": "SymbolTableNode", "implicit": true, "kind": "Mdef", "node": {".class": "Var", "flags": [], "fullname": "django.urls.resolvers.ResolverMatch.namespace", "name": "namespace", "type": {".class": "AnyType", "missing_import_name": null, "source_any": null, "type_of_any": 1}}}, "namespaces": {".class": "SymbolTableNode", "implicit": true, "kind": "Mdef", "node": {".class": "Var", "flags": [], "fullname": "django.urls.resolvers.ResolverMatch.namespaces", "name": "namespaces", "type": {".class": "AnyType", "missing_import_name": null, "source_any": null, "type_of_any": 1}}}, "route": {".class": "SymbolTableNode", "implicit": true, "kind": "Mdef", "node": {".class": "Var", "flags": [], "fullname": "django.urls.resolvers.ResolverMatch.route", "name": "route", "type": {".class": "AnyType", "missing_import_name": null, "source_any": null, "type_of_any": 1}}}, "url_name": {".class": "SymbolTableNode", "implicit": true, "kind": "Mdef", "node": {".class": "Var", "flags": [], "fullname": "django.urls.resolvers.ResolverMatch.url_name", "name": "url_name", "type": {".class": "AnyType", "missing_import_name": null, "source_any": null, "type_of_any": 1}}}, "view_name": {".class": "SymbolTableNode", "implicit": true, "kind": "Mdef", "node": {".class": "Var", "flags": [], "fullname": "django.urls.resolvers.ResolverMatch.view_name", "name": "view_name", "type": {".class": "AnyType", "missing_import_name": null, "source_any": null, "type_of_any": 1}}}}, "tuple_type": null, "type_vars": [], "typeddict_type": null}}, "RoutePattern": {".class": "SymbolTableNode", "kind": "Gdef", "node": {".class": "TypeInfo", "_promote": null, "abstract_attributes": [], "bases": ["django.urls.resolvers.CheckURLMixin"], "declared_metaclass": null, "defn": {".class": "ClassDef", "fullname": "django.urls.resolvers.RoutePattern", "name": "RoutePattern", "type_vars": []}, "flags": [], "fullname": "django.urls.resolvers.RoutePattern", "metaclass_type": null, "metadata": {}, "module_name": "django.urls.resolvers", "mro": ["django.urls.resolvers.RoutePattern", "django.urls.resolvers.CheckURLMixin", "builtins.object"], "names": {".class": "SymbolTable", "__init__": {".class": "SymbolTableNode", "kind": "Mdef", "node": {".class": "FuncDef", "arg_kinds": [0, 0, 1, 1], "arg_names": ["self", "route", "name", "is_endpoint"], "flags": [], "fullname": "django.urls.resolvers.RoutePattern.__init__", "name": "__init__", "type": null}}, "__str__": {".class": "SymbolTableNode", "kind": "Mdef", "node": {".class": "FuncDef", "arg_kinds": [0], "arg_names": ["self"], "flags": [], "fullname": "django.urls.resolvers.RoutePattern.__str__", "name": "__str__", "type": null}}, "_compile": {".class": "SymbolTableNode", "kind": "Mdef", "node": {".class": "FuncDef", "arg_kinds": [0, 0], "arg_names": ["self", "route"], "flags": [], "fullname": "django.urls.resolvers.RoutePattern._compile", "name": "_compile", "type": null}}, "_is_endpoint": {".class": "SymbolTableNode", "implicit": true, "kind": "Mdef", "node": {".class": "Var", "flags": [], "fullname": "django.urls.resolvers.RoutePattern._is_endpoint", "name": "_is_endpoint", "type": {".class": "AnyType", "missing_import_name": null, "source_any": null, "type_of_any": 1}}}, "_regex_dict": {".class": "SymbolTableNode", "implicit": true, "kind": "Mdef", "node": {".class": "Var", "flags": [], "fullname": "django.urls.resolvers.RoutePattern._regex_dict", "name": "_regex_dict", "type": {".class": "AnyType", "missing_import_name": null, "source_any": null, "type_of_any": 1}}}, "_route": {".class": "SymbolTableNode", "implicit": true, "kind": "Mdef", "node": {".class": "Var", "flags": [], "fullname": "django.urls.resolvers.RoutePattern._route", "name": "_route", "type": {".class": "AnyType", "missing_import_name": null, "source_any": null, "type_of_any": 1}}}, "check": {".class": "SymbolTableNode", "kind": "Mdef", "node": {".class": "FuncDef", "arg_kinds": [0], "arg_names": ["self"], "flags": [], "fullname": "django.urls.resolvers.RoutePattern.check", "name": "check", "type": null}}, "converters": {".class": "SymbolTableNode", "implicit": true, "kind": "Mdef", "node": {".class": "Var", "flags": [], "fullname": "django.urls.resolvers.RoutePattern.converters", "name": "converters", "type": {".class": "AnyType", "missing_import_name": null, "source_any": null, "type_of_any": 1}}}, "match": {".class": "SymbolTableNode", "kind": "Mdef", "node": {".class": "FuncDef", "arg_kinds": [0, 0], "arg_names": ["self", "path"], "flags": [], "fullname": "django.urls.resolvers.RoutePattern.match", "name": "match", "type": null}}, "name": {".class": "SymbolTableNode", "implicit": true, "kind": "Mdef", "node": {".class": "Var", "flags": [], "fullname": "django.urls.resolvers.RoutePattern.name", "name": "name", "type": {".class": "AnyType", "missing_import_name": null, "source_any": null, "type_of_any": 1}}}, "regex": {".class": "SymbolTableNode", "kind": "Mdef", "node": {".class": "Var", "flags": ["is_initialized_in_class"], "fullname": "django.urls.resolvers.RoutePattern.regex", "name": "regex", "type": "django.urls.resolvers.LocaleRegexDescriptor"}}}, "tuple_type": null, "type_vars": [], "typeddict_type": null}}, "URLPattern": {".class": "SymbolTableNode", "kind": "Gdef", "node": {".class": "TypeInfo", "_promote": null, "abstract_attributes": [], "bases": ["builtins.object"], "declared_metaclass": null, "defn": {".class": "ClassDef", "fullname": "django.urls.resolvers.URLPattern", "name": "URLPattern", "type_vars": []}, "flags": [], "fullname": "django.urls.resolvers.URLPattern", "metaclass_type": null, "metadata": {}, "module_name": "django.urls.resolvers", "mro": ["django.urls.resolvers.URLPattern", "builtins.object"], "names": {".class": "SymbolTable", "__init__": {".class": "SymbolTableNode", "kind": "Mdef", "node": {".class": "FuncDef", "arg_kinds": [0, 0, 0, 1, 1], "arg_names": ["self", "pattern", "callback", "default_args", "name"], "flags": [], "fullname": "django.urls.resolvers.URLPattern.__init__", "name": "__init__", "type": null}}, "__repr__": {".class": "SymbolTableNode", "kind": "Mdef", "node": {".class": "FuncDef", "arg_kinds": [0], "arg_names": ["self"], "flags": [], "fullname": "django.urls.resolvers.URLPattern.__repr__", "name": "__repr__", "type": null}}, "_check_pattern_name": {".class": "SymbolTableNode", "kind": "Mdef", "node": {".class": "FuncDef", "arg_kinds": [0], "arg_names": ["self"], "flags": [], "fullname": "django.urls.resolvers.URLPattern._check_pattern_name", "name": "_check_pattern_name", "type": null}}, "callback": {".class": "SymbolTableNode", "implicit": true, "kind": "Mdef", "node": {".class": "Var", "flags": [], "fullname": "django.urls.resolvers.URLPattern.callback", "name": "callback", "type": {".class": "AnyType", "missing_import_name": null, "source_any": null, "type_of_any": 1}}}, "check": {".class": "SymbolTableNode", "kind": "Mdef", "node": {".class": "FuncDef", "arg_kinds": [0], "arg_names": ["self"], "flags": [], "fullname": "django.urls.resolvers.URLPattern.check", "name": "check", "type": null}}, "default_args": {".class": "SymbolTableNode", "implicit": true, "kind": "Mdef", "node": {".class": "Var", "flags": [], "fullname": "django.urls.resolvers.URLPattern.default_args", "name": "default_args", "type": {".class": "AnyType", "missing_import_name": null, "source_any": null, "type_of_any": 1}}}, "lookup_str": {".class": "SymbolTableNode", "kind": "Mdef", "node": {".class": "Decorator", "func": {".class": "FuncDef", "arg_kinds": [0], "arg_names": ["self"], "flags": ["is_decorated"], "fullname": "django.urls.resolvers.URLPattern.lookup_str", "name": "lookup_str", "type": null}, "is_overload": false, "var": {".class": "Var", "flags": ["is_initialized_in_class", "is_ready"], "fullname": null, "name": "lookup_str", "type": "django.utils.functional.cached_property"}}}, "name": {".class": "SymbolTableNode", "implicit": true, "kind": "Mdef", "node": {".class": "Var", "flags": [], "fullname": "django.urls.resolvers.URLPattern.name", "name": "name", "type": {".class": "AnyType", "missing_import_name": null, "source_any": null, "type_of_any": 1}}}, "pattern": {".class": "SymbolTableNode", "implicit": true, "kind": "Mdef", "node": {".class": "Var", "flags": [], "fullname": "django.urls.resolvers.URLPattern.pattern", "name": "pattern", "type": {".class": "AnyType", "missing_import_name": null, "source_any": null, "type_of_any": 1}}}, "resolve": {".class": "SymbolTableNode", "kind": "Mdef", "node": {".class": "FuncDef", "arg_kinds": [0, 0], "arg_names": ["self", "path"], "flags": [], "fullname": "django.urls.resolvers.URLPattern.resolve", "name": "resolve", "type": null}}}, "tuple_type": null, "type_vars": [], "typeddict_type": null}}, "URLResolver": {".class": "SymbolTableNode", "kind": "Gdef", "node": {".class": "TypeInfo", "_promote": null, "abstract_attributes": [], "bases": ["builtins.object"], "declared_metaclass": null, "defn": {".class": "ClassDef", "fullname": "django.urls.resolvers.URLResolver", "name": "URLResolver", "type_vars": []}, "flags": [], "fullname": "django.urls.resolvers.URLResolver", "metaclass_type": null, "metadata": {}, "module_name": "django.urls.resolvers", "mro": ["django.urls.resolvers.URLResolver", "builtins.object"], "names": {".class": "SymbolTable", "__init__": {".class": "SymbolTableNode", "kind": "Mdef", "node": {".class": "FuncDef", "arg_kinds": [0, 0, 0, 1, 1, 1], "arg_names": ["self", "pattern", "urlconf_name", "default_kwargs", "app_name", "namespace"], "flags": [], "fullname": "django.urls.resolvers.URLResolver.__init__", "name": "__init__", "type": null}}, "__repr__": {".class": "SymbolTableNode", "kind": "Mdef", "node": {".class": "FuncDef", "arg_kinds": [0], "arg_names": ["self"], "flags": [], "fullname": "django.urls.resolvers.URLResolver.__repr__", "name": "__repr__", "type": null}}, "_app_dict": {".class": "SymbolTableNode", "implicit": true, "kind": "Mdef", "node": {".class": "Var", "flags": [], "fullname": "django.urls.resolvers.URLResolver._app_dict", "name": "_app_dict", "type": {".class": "AnyType", "missing_import_name": null, "source_any": null, "type_of_any": 1}}}, "_callback_strs": {".class": "SymbolTableNode", "implicit": true, "kind": "Mdef", "node": {".class": "Var", "flags": [], "fullname": "django.urls.resolvers.URLResolver._callback_strs", "name": "_callback_strs", "type": {".class": "AnyType", "missing_import_name": null, "source_any": null, "type_of_any": 1}}}, "_check_custom_error_handlers": {".class": "SymbolTableNode", "kind": "Mdef", "node": {".class": "FuncDef", "arg_kinds": [0], "arg_names": ["self"], "flags": [], "fullname": "django.urls.resolvers.URLResolver._check_custom_error_handlers", "name": "_check_custom_error_handlers", "type": null}}, "_is_callback": {".class": "SymbolTableNode", "kind": "Mdef", "node": {".class": "FuncDef", "arg_kinds": [0, 0], "arg_names": ["self", "name"], "flags": [], "fullname": "django.urls.resolvers.URLResolver._is_callback", "name": "_is_callback", "type": null}}, "_join_route": {".class": "SymbolTableNode", "kind": "Mdef", "node": {".class": "Decorator", "func": {".class": "FuncDef", "arg_kinds": [0, 0], "arg_names": ["route1", "route2"], "flags": ["is_static", "is_decorated"], "fullname": "django.urls.resolvers.URLResolver._join_route", "name": "_join_route", "type": null}, "is_overload": false, "var": {".class": "Var", "flags": ["is_initialized_in_class", "is_staticmethod", "is_ready"], "fullname": null, "name": "_join_route", "type": {".class": "CallableType", "arg_kinds": [0, 0], "arg_names": ["route1", "route2"], "arg_types": [{".class": "AnyType", "missing_import_name": null, "source_any": null, "type_of_any": 1}, {".class": "AnyType", "missing_import_name": null, "source_any": null, "type_of_any": 1}], "bound_args": [], "def_extras": {}, "fallback": "builtins.function", "implicit": true, "is_ellipsis_args": false, "name": "_join_route of URLResolver", "ret_type": {".class": "AnyType", "missing_import_name": null, "source_any": null, "type_of_any": 1}, "variables": []}}}}, "_local": {".class": "SymbolTableNode", "implicit": true, "kind": "Mdef", "node": {".class": "Var", "flags": [], "fullname": "django.urls.resolvers.URLResolver._local", "name": "_local", "type": {".class": "AnyType", "missing_import_name": null, "source_any": null, "type_of_any": 1}}}, "_namespace_dict": {".class": "SymbolTableNode", "implicit": true, "kind": "Mdef", "node": {".class": "Var", "flags": [], "fullname": "django.urls.resolvers.URLResolver._namespace_dict", "name": "_namespace_dict", "type": {".class": "AnyType", "missing_import_name": null, "source_any": null, "type_of_any": 1}}}, "_populate": {".class": "SymbolTableNode", "kind": "Mdef", "node": {".class": "FuncDef", "arg_kinds": [0], "arg_names": ["self"], "flags": [], "fullname": "django.urls.resolvers.URLResolver._populate", "name": "_populate", "type": null}}, "_populated": {".class": "SymbolTableNode", "implicit": true, "kind": "Mdef", "node": {".class": "Var", "flags": [], "fullname": "django.urls.resolvers.URLResolver._populated", "name": "_populated", "type": {".class": "AnyType", "missing_import_name": null, "source_any": null, "type_of_any": 1}}}, "_reverse_dict": {".class": "SymbolTableNode", "implicit": true, "kind": "Mdef", "node": {".class": "Var", "flags": [], "fullname": "django.urls.resolvers.URLResolver._reverse_dict", "name": "_reverse_dict", "type": {".class": "AnyType", "missing_import_name": null, "source_any": null, "type_of_any": 1}}}, "_reverse_with_prefix": {".class": "SymbolTableNode", "kind": "Mdef", "node": {".class": "FuncDef", "arg_kinds": [0, 0, 0, 2, 4], "arg_names": ["self", "lookup_view", "_prefix", "args", "kwargs"], "flags": [], "fullname": "django.urls.resolvers.URLResolver._reverse_with_prefix", "name": "_reverse_with_prefix", "type": null}}, "app_dict": {".class": "SymbolTableNode", "kind": "Mdef", "node": {".class": "Decorator", "func": {".class": "FuncDef", "arg_kinds": [0], "arg_names": ["self"], "flags": ["is_property", "is_decorated"], "fullname": "django.urls.resolvers.URLResolver.app_dict", "name": "app_dict", "type": null}, "is_overload": false, "var": {".class": "Var", "flags": ["is_initialized_in_class", "is_property", "is_ready"], "fullname": null, "name": "app_dict", "type": {".class": "CallableType", "arg_kinds": [0], "arg_names": ["self"], "arg_types": ["django.urls.resolvers.URLResolver"], "bound_args": [], "def_extras": {}, "fallback": "builtins.function", "implicit": true, "is_ellipsis_args": false, "name": "app_dict of URLResolver", "ret_type": {".class": "AnyType", "missing_import_name": null, "source_any": null, "type_of_any": 1}, "variables": []}}}}, "app_name": {".class": "SymbolTableNode", "implicit": true, "kind": "Mdef", "node": {".class": "Var", "flags": [], "fullname": "django.urls.resolvers.URLResolver.app_name", "name": "app_name", "type": {".class": "AnyType", "missing_import_name": null, "source_any": null, "type_of_any": 1}}}, "callback": {".class": "SymbolTableNode", "implicit": true, "kind": "Mdef", "node": {".class": "Var", "flags": [], "fullname": "django.urls.resolvers.URLResolver.callback", "name": "callback", "type": {".class": "AnyType", "missing_import_name": null, "source_any": null, "type_of_any": 1}}}, "check": {".class": "SymbolTableNode", "kind": "Mdef", "node": {".class": "FuncDef", "arg_kinds": [0], "arg_names": ["self"], "flags": [], "fullname": "django.urls.resolvers.URLResolver.check", "name": "check", "type": null}}, "default_kwargs": {".class": "SymbolTableNode", "implicit": true, "kind": "Mdef", "node": {".class": "Var", "flags": [], "fullname": "django.urls.resolvers.URLResolver.default_kwargs", "name": "default_kwargs", "type": {".class": "AnyType", "missing_import_name": null, "source_any": null, "type_of_any": 1}}}, "namespace": {".class": "SymbolTableNode", "implicit": true, "kind": "Mdef", "node": {".class": "Var", "flags": [], "fullname": "django.urls.resolvers.URLResolver.namespace", "name": "namespace", "type": {".class": "AnyType", "missing_import_name": null, "source_any": null, "type_of_any": 1}}}, "namespace_dict": {".class": "SymbolTableNode", "kind": "Mdef", "node": {".class": "Decorator", "func": {".class": "FuncDef", "arg_kinds": [0], "arg_names": ["self"], "flags": ["is_property", "is_decorated"], "fullname": "django.urls.resolvers.URLResolver.namespace_dict", "name": "namespace_dict", "type": null}, "is_overload": false, "var": {".class": "Var", "flags": ["is_initialized_in_class", "is_property", "is_ready"], "fullname": null, "name": "namespace_dict", "type": {".class": "CallableType", "arg_kinds": [0], "arg_names": ["self"], "arg_types": ["django.urls.resolvers.URLResolver"], "bound_args": [], "def_extras": {}, "fallback": "builtins.function", "implicit": true, "is_ellipsis_args": false, "name": "namespace_dict of URLResolver", "ret_type": {".class": "AnyType", "missing_import_name": null, "source_any": null, "type_of_any": 1}, "variables": []}}}}, "pattern": {".class": "SymbolTableNode", "implicit": true, "kind": "Mdef", "node": {".class": "Var", "flags": [], "fullname": "django.urls.resolvers.URLResolver.pattern", "name": "pattern", "type": {".class": "AnyType", "missing_import_name": null, "source_any": null, "type_of_any": 1}}}, "resolve": {".class": "SymbolTableNode", "kind": "Mdef", "node": {".class": "FuncDef", "arg_kinds": [0, 0], "arg_names": ["self", "path"], "flags": [], "fullname": "django.urls.resolvers.URLResolver.resolve", "name": "resolve", "type": null}}, "resolve_error_handler": {".class": "SymbolTableNode", "kind": "Mdef", "node": {".class": "FuncDef", "arg_kinds": [0, 0], "arg_names": ["self", "view_type"], "flags": [], "fullname": "django.urls.resolvers.URLResolver.resolve_error_handler", "name": "resolve_error_handler", "type": null}}, "reverse": {".class": "SymbolTableNode", "kind": "Mdef", "node": {".class": "FuncDef", "arg_kinds": [0, 0, 2, 4], "arg_names": ["self", "lookup_view", "args", "kwargs"], "flags": [], "fullname": "django.urls.resolvers.URLResolver.reverse", "name": "reverse", "type": null}}, "reverse_dict": {".class": "SymbolTableNode", "kind": "Mdef", "node": {".class": "Decorator", "func": {".class": "FuncDef", "arg_kinds": [0], "arg_names": ["self"], "flags": ["is_property", "is_decorated"], "fullname": "django.urls.resolvers.URLResolver.reverse_dict", "name": "reverse_dict", "type": null}, "is_overload": false, "var": {".class": "Var", "flags": ["is_initialized_in_class", "is_property", "is_ready"], "fullname": null, "name": "reverse_dict", "type": {".class": "CallableType", "arg_kinds": [0], "arg_names": ["self"], "arg_types": ["django.urls.resolvers.URLResolver"], "bound_args": [], "def_extras": {}, "fallback": "builtins.function", "implicit": true, "is_ellipsis_args": false, "name": "reverse_dict of URLResolver", "ret_type": {".class": "AnyType", "missing_import_name": null, "source_any": null, "type_of_any": 1}, "variables": []}}}}, "url_patterns": {".class": "SymbolTableNode", "kind": "Mdef", "node": {".class": "Decorator", "func": {".class": "FuncDef", "arg_kinds": [0], "arg_names": ["self"], "flags": ["is_decorated"], "fullname": "django.urls.resolvers.URLResolver.url_patterns", "name": "url_patterns", "type": null}, "is_overload": false, "var": {".class": "Var", "flags": ["is_initialized_in_class", "is_ready"], "fullname": null, "name": "url_patterns", "type": "django.utils.functional.cached_property"}}}, "urlconf_module": {".class": "SymbolTableNode", "kind": "Mdef", "node": {".class": "Decorator", "func": {".class": "FuncDef", "arg_kinds": [0], "arg_names": ["self"], "flags": ["is_decorated"], "fullname": "django.urls.resolvers.URLResolver.urlconf_module", "name": "urlconf_module", "type": null}, "is_overload": false, "var": {".class": "Var", "flags": ["is_initialized_in_class", "is_ready"], "fullname": null, "name": "urlconf_module", "type": "django.utils.functional.cached_property"}}}, "urlconf_name": {".class": "SymbolTableNode", "implicit": true, "kind": "Mdef", "node": {".class": "Var", "flags": [], "fullname": "django.urls.resolvers.URLResolver.urlconf_name", "name": "urlconf_name", "type": {".class": "AnyType", "missing_import_name": null, "source_any": null, "type_of_any": 1}}}}, "tuple_type": null, "type_vars": [], "typeddict_type": null}}, "ViewDoesNotExist": {".class": "SymbolTableNode", "cross_ref": "django.core.exceptions.ViewDoesNotExist", "kind": "Gdef"}, "Warning": {".class": "SymbolTableNode", "cross_ref": "django.core.checks.messages.Warning", "kind": "Gdef"}, "_PATH_PARAMETER_COMPONENT_RE": {".class": "SymbolTableNode", "kind": "Gdef", "node": {".class": "Var", "flags": [], "fullname": "django.urls.resolvers._PATH_PARAMETER_COMPONENT_RE", "name": "_PATH_PARAMETER_COMPONENT_RE", "type": {".class": "AnyType", "missing_import_name": null, "source_any": null, "type_of_any": 1}}}, "__doc__": {".class": "SymbolTableNode", "kind": "Gdef", "node": {".class": "Var", "flags": ["is_ready"], "fullname": "django.urls.resolvers.__doc__", "name": "__doc__", "type": "builtins.str"}}, "__file__": {".class": "SymbolTableNode", "kind": "Gdef", "node": {".class": "Var", "flags": ["is_ready"], "fullname": "django.urls.resolvers.__file__", "name": "__file__", "type": "builtins.str"}}, "__name__": {".class": "SymbolTableNode", "kind": "Gdef", "node": {".class": "Var", "flags": ["is_ready"], "fullname": "django.urls.resolvers.__name__", "name": "__name__", "type": "builtins.str"}}, "__package__": {".class": "SymbolTableNode", "kind": "Gdef", "node": {".class": "Var", "flags": ["is_ready"], "fullname": "django.urls.resolvers.__package__", "name": "__package__", "type": "builtins.str"}}, "_get_cached_resolver": {".class": "SymbolTableNode", "kind": "Gdef", "node": {".class": "Decorator", "func": {".class": "FuncDef", "arg_kinds": [1], "arg_names": ["urlconf"], "flags": ["is_decorated"], "fullname": "django.urls.resolvers._get_cached_resolver", "name": "_get_cached_resolver", "type": null}, "is_overload": false, "var": {".class": "Var", "flags": ["is_ready"], "fullname": null, "name": "_get_cached_resolver", "type": {".class": "Instance", "args": [{".class": "AnyType", "missing_import_name": null, "source_any": {".class": "AnyType", "missing_import_name": null, "source_any": null, "type_of_any": 1}, "type_of_any": 7}], "type_ref": "functools._lru_cache_wrapper"}}}}, "_lazy_re_compile": {".class": "SymbolTableNode", "cross_ref": "django.utils.regex_helper._lazy_re_compile", "kind": "Gdef"}, "_route_to_regex": {".class": "SymbolTableNode", "kind": "Gdef", "node": {".class": "FuncDef", "arg_kinds": [0, 1], "arg_names": ["route", "is_endpoint"], "flags": [], "fullname": "django.urls.resolvers._route_to_regex", "name": "_route_to_regex", "type": null}}, "cached_property": {".class": "SymbolTableNode", "cross_ref": "django.utils.functional.cached_property", "kind": "Gdef"}, "check_resolver": {".class": "SymbolTableNode", "cross_ref": "django.core.checks.urls.check_resolver", "kind": "Gdef"}, "escape_leading_slashes": {".class": "SymbolTableNode", "cross_ref": "django.utils.http.escape_leading_slashes", "kind": "Gdef"}, "functools": {".class": "SymbolTableNode", "cross_ref": "functools", "kind": "Gdef"}, "get_callable": {".class": "SymbolTableNode", "cross_ref": "django.urls.utils.get_callable", "kind": "Gdef"}, "get_converter": {".class": "SymbolTableNode", "cross_ref": "django.urls.converters.get_converter", "kind": "Gdef"}, "get_language": {".class": "SymbolTableNode", "cross_ref": "django.utils.translation.get_language", "kind": "Gdef"}, "get_ns_resolver": {".class": "SymbolTableNode", "kind": "Gdef", "node": {".class": "Decorator", "func": {".class": "FuncDef", "arg_kinds": [0, 0, 0], "arg_names": ["ns_pattern", "resolver", "converters"], "flags": ["is_decorated"], "fullname": "django.urls.resolvers.get_ns_resolver", "name": "get_ns_resolver", "type": null}, "is_overload": false, "var": {".class": "Var", "flags": ["is_ready"], "fullname": null, "name": "get_ns_resolver", "type": {".class": "Instance", "args": [{".class": "AnyType", "missing_import_name": null, "source_any": {".class": "AnyType", "missing_import_name": null, "source_any": null, "type_of_any": 1}, "type_of_any": 7}], "type_ref": "functools._lru_cache_wrapper"}}}}, "get_resolver": {".class": "SymbolTableNode", "kind": "Gdef", "node": {".class": "FuncDef", "arg_kinds": [1], "arg_names": ["urlconf"], "flags": [], "fullname": "django.urls.resolvers.get_resolver", "name": "get_resolver", "type": null}}, "import_module": {".class": "SymbolTableNode", "cross_ref": "importlib.import_module", "kind": "Gdef"}, "inspect": {".class": "SymbolTableNode", "cross_ref": "inspect", "kind": "Gdef"}, "normalize": {".class": "SymbolTableNode", "cross_ref": "django.utils.regex_helper.normalize", "kind": "Gdef"}, "quote": {".class": "SymbolTableNode", "cross_ref": "urllib.parse.quote", "kind": "Gdef"}, "re": {".class": "SymbolTableNode", "cross_ref": "re", "kind": "Gdef"}, "settings": {".class": "SymbolTableNode", "cross_ref": "django.conf.settings", "kind": "Gdef"}, "string": {".class": "SymbolTableNode", "cross_ref": "string", "kind": "Gdef"}}, "path": "/home/ibrahim/opensrc/django/django/urls/resolvers.py"}